{
"Class" : "org.jsoup.nodes.Document", 
"Methods" : [{ "Name" : "title" ,
"Duas" : 3,
"0" :  "(68,(69,69), titleEl)",
"1" :  "(68,(69,69), titleEl)",
"2" :  "(68,69, titleEl)"},{ "Name" : "title" ,
"Duas" : 6,
"0" :  "(78,81, this)",
"1" :  "(78,83, title)",
"2" :  "(78,81, title)",
"3" :  "(79,(80,81), titleEl)",
"4" :  "(79,(80,83), titleEl)",
"5" :  "(79,83, titleEl)"},{ "Name" : "normalise" ,
"Duas" : 23,
"0" :  "(102,(105,106), this)",
"1" :  "(102,(105,107), this)",
"2" :  "(102,(107,108), this)",
"3" :  "(102,(107,112), this)",
"4" :  "(102,112, this)",
"5" :  "(102,113, this)",
"6" :  "(102,114, this)",
"7" :  "(102,116, this)",
"8" :  "(102,117, this)",
"9" :  "(102,119, this)",
"10" :  "(102,104, this)",
"11" :  "(102,(103,104), htmlEl)",
"12" :  "(102,(103,105), htmlEl)",
"13" :  "(102,113, htmlEl)",
"14" :  "(102,116, htmlEl)",
"15" :  "(102,117, htmlEl)",
"16" :  "(102,108, htmlEl)",
"17" :  "(102,106, htmlEl)",
"18" :  "(104,113, htmlEl)",
"19" :  "(104,116, htmlEl)",
"20" :  "(104,117, htmlEl)",
"21" :  "(104,108, htmlEl)",
"22" :  "(104,106, htmlEl)"},{ "Name" : "normaliseTextNodes" ,
"Duas" : 23,
"0" :  "(124,136, this)",
"1" :  "(124,137, this)",
"2" :  "(124,135, element)",
"3" :  "(124,133, toMove)",
"4" :  "(124,134, toMove)",
"5" :  "(124,129, toMove)",
"6" :  "(125,(125,125), i$)",
"7" :  "(125,(125,133), i$)",
"8" :  "(125,125, i$)",
"9" :  "(125,(126,127), node)",
"10" :  "(125,(126,131), node)",
"11" :  "(125,127, node)",
"12" :  "(127,(128,129), tn)",
"13" :  "(127,(128,131), tn)",
"14" :  "(127,129, tn)",
"15" :  "(133,(133,134), i)",
"16" :  "(133,(133,139), i)",
"17" :  "(133,134, i)",
"18" :  "(133,133, i)",
"19" :  "(133,(133,134), i)",
"20" :  "(133,(133,139), i)",
"21" :  "(133,134, i)",
"22" :  "(133,133, i)"},{ "Name" : "normaliseStructure" ,
"Duas" : 29,
"0" :  "(143,(158,159), htmlEl)",
"1" :  "(143,(158,161), htmlEl)",
"2" :  "(143,159, htmlEl)",
"3" :  "(143,(145,146), elements)",
"4" :  "(143,(145,158), elements)",
"5" :  "(143,(147,148), elements)",
"6" :  "(143,(147,154), elements)",
"7" :  "(143,148, elements)",
"8" :  "(144,(158,159), master)",
"9" :  "(144,(158,161), master)",
"10" :  "(144,159, master)",
"11" :  "(144,155, master)",
"12" :  "(146,154, toMove)",
"13" :  "(146,150, toMove)",
"14" :  "(147,(147,148), i)",
"15" :  "(147,(147,154), i)",
"16" :  "(147,148, i)",
"17" :  "(147,147, i)",
"18" :  "(148,151, dupe)",
"19" :  "(149,(149,149), i$)",
"20" :  "(149,(149,151), i$)",
"21" :  "(149,149, i$)",
"22" :  "(147,(147,148), i)",
"23" :  "(147,(147,154), i)",
"24" :  "(147,148, i)",
"25" :  "(147,147, i)",
"26" :  "(154,(154,154), i$)",
"27" :  "(154,(154,158), i$)",
"28" :  "(154,154, i$)"},{ "Name" : "findFirstElementByTagName" ,
"Duas" : 15,
"0" :  "(165,169, this)",
"1" :  "(165,(165,166), tag)",
"2" :  "(165,(165,168), tag)",
"3" :  "(165,169, tag)",
"4" :  "(165,(165,166), node)",
"5" :  "(165,(165,168), node)",
"6" :  "(165,168, node)",
"7" :  "(165,166, node)",
"8" :  "(165,168, node.childNodes)",
"9" :  "(168,(168,168), i$)",
"10" :  "(168,(168,174), i$)",
"11" :  "(168,168, i$)",
"12" :  "(169,(170,171), found)",
"13" :  "(169,(170,172), found)",
"14" :  "(169,171, found)"}]
}