{
"Class" : "org.joda.time.format.DateTimeFormatterBuilder", 
"Methods" : [{ "Name" : "toFormatter" ,
"Duas" : 22,
"0" :  "(104,(106,107), this)",
"1" :  "(104,(106,109), this)",
"2" :  "(104,(110,111), this)",
"3" :  "(104,(110,113), this)",
"4" :  "(104,(106,107), f)",
"5" :  "(104,(106,109), f)",
"6" :  "(104,(110,111), f)",
"7" :  "(104,(110,113), f)",
"8" :  "(104,111, f)",
"9" :  "(104,107, f)",
"10" :  "(105,(113,113), printer)",
"11" :  "(105,(113,114), printer)",
"12" :  "(105,114, printer)",
"13" :  "(107,(113,113), printer)",
"14" :  "(107,(113,114), printer)",
"15" :  "(107,114, printer)",
"16" :  "(109,114, parser)",
"17" :  "(109,(113,114), parser)",
"18" :  "(109,(113,116), parser)",
"19" :  "(111,114, parser)",
"20" :  "(111,(113,114), parser)",
"21" :  "(111,(113,116), parser)"},{ "Name" : "toPrinter" ,
"Duas" : 5,
"0" :  "(132,(133,134), this)",
"1" :  "(132,(133,136), this)",
"2" :  "(132,(133,134), f)",
"3" :  "(132,(133,136), f)",
"4" :  "(132,134, f)"},{ "Name" : "toParser" ,
"Duas" : 5,
"0" :  "(152,(153,154), this)",
"1" :  "(152,(153,156), this)",
"2" :  "(152,(153,154), f)",
"3" :  "(152,(153,156), f)",
"4" :  "(152,154, f)"},{ "Name" : "append" ,
"Duas" : 4,
"0" :  "(209,212, this)",
"1" :  "(209,(209,210), formatter)",
"2" :  "(209,(209,212), formatter)",
"3" :  "(209,212, formatter)"},{ "Name" : "append" ,
"Duas" : 40,
"0" :  "(273,296, this)",
"1" :  "(273,284, this)",
"2" :  "(273,274, this)",
"3" :  "(273,(273,274), printer)",
"4" :  "(273,(273,276), printer)",
"5" :  "(273,296, printer)",
"6" :  "(273,284, printer)",
"7" :  "(273,274, printer)",
"8" :  "(273,(276,277), parsers)",
"9" :  "(273,(276,279), parsers)",
"10" :  "(273,279, parsers)",
"11" :  "(273,294, parsers)",
"12" :  "(273,290, parsers)",
"13" :  "(273,(290,291), parsers)",
"14" :  "(273,(290,289), parsers)",
"15" :  "(273,(281,282), parsers)",
"16" :  "(273,(281,284), parsers)",
"17" :  "(273,284, parsers)",
"18" :  "(279,(280,281), length)",
"19" :  "(279,(280,287), length)",
"20" :  "(279,287, length)",
"21" :  "(279,(289,290), length)",
"22" :  "(279,(289,294), length)",
"23" :  "(287,294, copyOfParsers)",
"24" :  "(287,296, copyOfParsers)",
"25" :  "(287,290, copyOfParsers)",
"26" :  "(289,(289,290), i)",
"27" :  "(289,(289,294), i)",
"28" :  "(289,294, i)",
"29" :  "(289,290, i)",
"30" :  "(289,(290,291), i)",
"31" :  "(289,(290,289), i)",
"32" :  "(289,289, i)",
"33" :  "(289,(289,290), i)",
"34" :  "(289,(289,294), i)",
"35" :  "(289,294, i)",
"36" :  "(289,290, i)",
"37" :  "(289,(290,291), i)",
"38" :  "(289,(290,289), i)",
"39" :  "(289,289, i)"},{ "Name" : "checkParser" ,
"Duas" : 2,
"0" :  "(319,(319,320), parser)",
"1" :  "(319,(319,322), parser)"},{ "Name" : "checkPrinter" ,
"Duas" : 2,
"0" :  "(330,(330,331), printer)",
"1" :  "(330,(330,333), printer)"},{ "Name" : "appendLiteral" ,
"Duas" : 10,
"0" :  "(370,377, this)",
"1" :  "(370,375, this)",
"2" :  "(370,379, this)",
"3" :  "(370,(370,371), text)",
"4" :  "(370,(370,373), text)",
"5" :  "(370,(373,379), text)",
"6" :  "(370,(373,375), text)",
"7" :  "(370,(373,377), text)",
"8" :  "(370,377, text)",
"9" :  "(370,379, text)"},{ "Name" : "appendDecimal" ,
"Duas" : 24,
"0" :  "(396,408, this)",
"1" :  "(396,406, this)",
"2" :  "(396,(396,397), fieldType)",
"3" :  "(396,(396,399), fieldType)",
"4" :  "(396,408, fieldType)",
"5" :  "(396,406, fieldType)",
"6" :  "(396,(399,400), minDigits)",
"7" :  "(396,(399,402), minDigits)",
"8" :  "(396,(402,402), minDigits)",
"9" :  "(396,(402,403), minDigits)",
"10" :  "(396,(405,406), minDigits)",
"11" :  "(396,(405,408), minDigits)",
"12" :  "(396,408, minDigits)",
"13" :  "(396,400, minDigits)",
"14" :  "(396,(399,400), maxDigits)",
"15" :  "(396,(399,402), maxDigits)",
"16" :  "(396,(402,403), maxDigits)",
"17" :  "(396,(402,405), maxDigits)",
"18" :  "(396,408, maxDigits)",
"19" :  "(396,406, maxDigits)",
"20" :  "(400,(402,403), maxDigits)",
"21" :  "(400,(402,405), maxDigits)",
"22" :  "(400,408, maxDigits)",
"23" :  "(400,406, maxDigits)"},{ "Name" : "appendFixedDecimal" ,
"Duas" : 8,
"0" :  "(426,432, this)",
"1" :  "(426,(426,427), fieldType)",
"2" :  "(426,(426,429), fieldType)",
"3" :  "(426,432, fieldType)",
"4" :  "(426,(429,430), numDigits)",
"5" :  "(426,(429,432), numDigits)",
"6" :  "(426,432, numDigits)",
"7" :  "(426,430, numDigits)"},{ "Name" : "appendSignedDecimal" ,
"Duas" : 24,
"0" :  "(448,460, this)",
"1" :  "(448,458, this)",
"2" :  "(448,(448,449), fieldType)",
"3" :  "(448,(448,451), fieldType)",
"4" :  "(448,460, fieldType)",
"5" :  "(448,458, fieldType)",
"6" :  "(448,(451,452), minDigits)",
"7" :  "(448,(451,454), minDigits)",
"8" :  "(448,(454,454), minDigits)",
"9" :  "(448,(454,455), minDigits)",
"10" :  "(448,(457,458), minDigits)",
"11" :  "(448,(457,460), minDigits)",
"12" :  "(448,460, minDigits)",
"13" :  "(448,452, minDigits)",
"14" :  "(448,(451,452), maxDigits)",
"15" :  "(448,(451,454), maxDigits)",
"16" :  "(448,(454,455), maxDigits)",
"17" :  "(448,(454,457), maxDigits)",
"18" :  "(448,460, maxDigits)",
"19" :  "(448,458, maxDigits)",
"20" :  "(452,(454,455), maxDigits)",
"21" :  "(452,(454,457), maxDigits)",
"22" :  "(452,460, maxDigits)",
"23" :  "(452,458, maxDigits)"},{ "Name" : "appendFixedSignedDecimal" ,
"Duas" : 8,
"0" :  "(478,484, this)",
"1" :  "(478,(478,479), fieldType)",
"2" :  "(478,(478,481), fieldType)",
"3" :  "(478,484, fieldType)",
"4" :  "(478,(481,482), numDigits)",
"5" :  "(478,(481,484), numDigits)",
"6" :  "(478,484, numDigits)",
"7" :  "(478,482, numDigits)"},{ "Name" : "appendText" ,
"Duas" : 4,
"0" :  "(496,499, this)",
"1" :  "(496,(496,497), fieldType)",
"2" :  "(496,(496,499), fieldType)",
"3" :  "(496,499, fieldType)"},{ "Name" : "appendShortText" ,
"Duas" : 4,
"0" :  "(511,514, this)",
"1" :  "(511,(511,512), fieldType)",
"2" :  "(511,(511,514), fieldType)",
"3" :  "(511,514, fieldType)"},{ "Name" : "appendFraction" ,
"Duas" : 18,
"0" :  "(532,541, this)",
"1" :  "(532,(532,533), fieldType)",
"2" :  "(532,(532,535), fieldType)",
"3" :  "(532,541, fieldType)",
"4" :  "(532,(535,536), minDigits)",
"5" :  "(532,(535,538), minDigits)",
"6" :  "(532,(538,538), minDigits)",
"7" :  "(532,(538,539), minDigits)",
"8" :  "(532,541, minDigits)",
"9" :  "(532,536, minDigits)",
"10" :  "(532,(535,536), maxDigits)",
"11" :  "(532,(535,538), maxDigits)",
"12" :  "(532,(538,539), maxDigits)",
"13" :  "(532,(538,541), maxDigits)",
"14" :  "(532,541, maxDigits)",
"15" :  "(536,(538,539), maxDigits)",
"16" :  "(536,(538,541), maxDigits)",
"17" :  "(536,541, maxDigits)"},{ "Name" : "getFormatter" ,
"Duas" : 37,
"0" :  "(1100,(1103,1104), this)",
"1" :  "(1100,(1103,1116), this)",
"2" :  "(1100,1120, this)",
"3" :  "(1100,1117, this)",
"4" :  "(1100,1104, this)",
"5" :  "(1100,1105, this)",
"6" :  "(1100,(1103,1104), this.iElementPairs)",
"7" :  "(1100,(1103,1116), this.iElementPairs)",
"8" :  "(1100,1117, this.iElementPairs)",
"9" :  "(1100,1104, this.iElementPairs)",
"10" :  "(1100,1105, this.iElementPairs)",
"11" :  "(1100,(1102,1103), f)",
"12" :  "(1100,(1102,1123), f)",
"13" :  "(1100,1123, f)",
"14" :  "(1100,(1116,1117), f)",
"15" :  "(1100,(1116,1120), f)",
"16" :  "(1100,1120, f)",
"17" :  "(1104,(1107,1108), printer)",
"18" :  "(1104,(1107,1112), printer)",
"19" :  "(1104,(1108,1108), printer)",
"20" :  "(1104,(1108,1109), printer)",
"21" :  "(1104,1109, printer)",
"22" :  "(1105,1112, parser)",
"23" :  "(1105,(1108,1108), parser)",
"24" :  "(1105,(1108,1109), parser)",
"25" :  "(1105,(1108,1109), parser)",
"26" :  "(1105,(1108,1116), parser)",
"27" :  "(1109,(1116,1117), f)",
"28" :  "(1109,(1116,1120), f)",
"29" :  "(1109,1120, f)",
"30" :  "(1109,1123, f)",
"31" :  "(1112,(1116,1117), f)",
"32" :  "(1112,(1116,1120), f)",
"33" :  "(1112,1120, f)",
"34" :  "(1112,1123, f)",
"35" :  "(1117,1120, f)",
"36" :  "(1117,1123, f)"},{ "Name" : "isPrinter" ,
"Duas" : 5,
"0" :  "(1127,(1127,1128), f)",
"1" :  "(1127,(1127,1133), f)",
"2" :  "(1127,(1128,1129), f)",
"3" :  "(1127,(1128,1131), f)",
"4" :  "(1127,1129, f)"},{ "Name" : "isParser" ,
"Duas" : 5,
"0" :  "(1137,(1137,1138), f)",
"1" :  "(1137,(1137,1143), f)",
"2" :  "(1137,(1138,1139), f)",
"3" :  "(1137,(1138,1141), f)",
"4" :  "(1137,1139, f)"},{ "Name" : "isFormatter" ,
"Duas" : 8,
"0" :  "(1147,(1147,1147), this)",
"1" :  "(1147,(1147,1147), this)",
"2" :  "(1147,(1147,1147), this)",
"3" :  "(1147,(1147,1147), this)",
"4" :  "(1147,(1147,1147), f)",
"5" :  "(1147,(1147,1147), f)",
"6" :  "(1147,(1147,1147), f)",
"7" :  "(1147,(1147,1147), f)"},{ "Name" : "appendUnknownString" ,
"Duas" : 5,
"0" :  "(1151,1152, buf)",
"1" :  "(1151,1151, i)",
"2" :  "(1151,(1151,1152), i)",
"3" :  "(1151,(1151,1154), i)",
"4" :  "(1151,1151, i)"},{ "Name" : "printUnknownString" ,
"Duas" : 5,
"0" :  "(1157,1158, out)",
"1" :  "(1157,1157, i)",
"2" :  "(1157,(1157,1158), i)",
"3" :  "(1157,(1157,1160), i)",
"4" :  "(1157,1157, i)"}]
}