{
"Class" : "org.apache.commons.compress.archivers.sevenz.Coders", 
"Methods" : [{ "Name" : "addDecoder" ,
"Duas" : 26,
"0" :  "(46,48, is)",
"1" :  "(46,51, coder)",
"2" :  "(46,(47,48), coder)",
"3" :  "(46,(47,46), coder)",
"4" :  "(46,48, coder)",
"5" :  "(46,48, password)",
"6" :  "(46,51, coder.decompressionMethodId)",
"7" :  "(46,(47,48), coder.decompressionMethodId)",
"8" :  "(46,(47,46), coder.decompressionMethodId)",
"9" :  "(46,46, arr$)",
"10" :  "(46,(46,46), len$)",
"11" :  "(46,(46,51), len$)",
"12" :  "(46,(46,46), i$)",
"13" :  "(46,(46,51), i$)",
"14" :  "(46,46, i$)",
"15" :  "(46,46, i$)",
"16" :  "(46,(47,48), coderId)",
"17" :  "(46,(47,46), coderId)",
"18" :  "(46,48, coderId)",
"19" :  "(46,(47,48), coderId.method)",
"20" :  "(46,(47,46), coderId.method)",
"21" :  "(46,48, coderId.coder)",
"22" :  "(46,(46,46), i$)",
"23" :  "(46,(46,51), i$)",
"24" :  "(46,46, i$)",
"25" :  "(46,46, i$)"},{ "Name" : "addEncoder" ,
"Duas" : 22,
"0" :  "(57,59, out)",
"1" :  "(57,62, method)",
"2" :  "(57,(58,59), method)",
"3" :  "(57,(58,57), method)",
"4" :  "(57,59, password)",
"5" :  "(57,57, arr$)",
"6" :  "(57,(57,57), len$)",
"7" :  "(57,(57,62), len$)",
"8" :  "(57,(57,57), i$)",
"9" :  "(57,(57,62), i$)",
"10" :  "(57,57, i$)",
"11" :  "(57,57, i$)",
"12" :  "(57,(58,59), coderId)",
"13" :  "(57,(58,57), coderId)",
"14" :  "(57,59, coderId)",
"15" :  "(57,(58,59), coderId.method)",
"16" :  "(57,(58,57), coderId.method)",
"17" :  "(57,59, coderId.coder)",
"18" :  "(57,(57,57), i$)",
"19" :  "(57,(57,62), i$)",
"20" :  "(57,57, i$)",
"21" :  "(57,57, i$)"}]
}