{
"Class" : "com.google.gson.stream.JsonReader", 
"Methods" : [{ "Name" : "<init>" ,
"Duas" : 4,
"0" :  "(289,293, this)",
"1" :  "(289,(290,291), in)",
"2" :  "(289,(290,293), in)",
"3" :  "(289,293, in)"},{ "Name" : "beginArray" ,
"Duas" : 13,
"0" :  "(341,350, this)",
"1" :  "(341,346, this)",
"2" :  "(341,347, this)",
"3" :  "(341,348, this)",
"4" :  "(341,343, this)",
"5" :  "(341,347, this.stackSize)",
"6" :  "(341,347, this.pathIndices)",
"7" :  "(341,(342,343), p)",
"8" :  "(341,(342,345), p)",
"9" :  "(341,(345,346), p)",
"10" :  "(341,(345,350), p)",
"11" :  "(343,(345,346), p)",
"12" :  "(343,(345,350), p)"},{ "Name" : "endArray" ,
"Duas" : 13,
"0" :  "(360,369, this)",
"1" :  "(360,365, this)",
"2" :  "(360,366, this)",
"3" :  "(360,367, this)",
"4" :  "(360,362, this)",
"5" :  "(360,365, this.stackSize)",
"6" :  "(360,366, this.pathIndices)",
"7" :  "(360,(361,362), p)",
"8" :  "(360,(361,364), p)",
"9" :  "(360,(364,365), p)",
"10" :  "(360,(364,369), p)",
"11" :  "(362,(364,365), p)",
"12" :  "(362,(364,369), p)"},{ "Name" : "beginObject" ,
"Duas" : 10,
"0" :  "(379,387, this)",
"1" :  "(379,384, this)",
"2" :  "(379,385, this)",
"3" :  "(379,381, this)",
"4" :  "(379,(380,381), p)",
"5" :  "(379,(380,383), p)",
"6" :  "(379,(383,384), p)",
"7" :  "(379,(383,387), p)",
"8" :  "(381,(383,384), p)",
"9" :  "(381,(383,387), p)"},{ "Name" : "endObject" ,
"Duas" : 15,
"0" :  "(397,407, this)",
"1" :  "(397,402, this)",
"2" :  "(397,403, this)",
"3" :  "(397,404, this)",
"4" :  "(397,405, this)",
"5" :  "(397,399, this)",
"6" :  "(397,402, this.stackSize)",
"7" :  "(397,403, this.pathNames)",
"8" :  "(397,404, this.pathIndices)",
"9" :  "(397,(398,399), p)",
"10" :  "(397,(398,401), p)",
"11" :  "(397,(401,402), p)",
"12" :  "(397,(401,407), p)",
"13" :  "(399,(401,402), p)",
"14" :  "(399,(401,407), p)"},{ "Name" : "hasNext" ,
"Duas" : 11,
"0" :  "(416,418, this)",
"1" :  "(416,(417,418), p)",
"2" :  "(416,(417,420), p)",
"3" :  "(416,(420,420), p)",
"4" :  "(416,(420,420), p)",
"5" :  "(416,(420,420), p)",
"6" :  "(416,(420,420), p)",
"7" :  "(418,(420,420), p)",
"8" :  "(418,(420,420), p)",
"9" :  "(418,(420,420), p)",
"10" :  "(418,(420,420), p)"},{ "Name" : "peek" ,
"Duas" : 35,
"0" :  "(427,429, this)",
"1" :  "(427,434, BEGIN_OBJECT)",
"2" :  "(427,436, END_OBJECT)",
"3" :  "(427,438, BEGIN_ARRAY)",
"4" :  "(427,440, END_ARRAY)",
"5" :  "(427,444, NAME)",
"6" :  "(427,447, BOOLEAN)",
"7" :  "(427,449, NULL)",
"8" :  "(427,454, STRING)",
"9" :  "(427,457, NUMBER)",
"10" :  "(427,459, END_DOCUMENT)",
"11" :  "(427,(428,429), p)",
"12" :  "(427,(428,432), p)",
"13" :  "(427,(432,461), p)",
"14" :  "(427,(432,434), p)",
"15" :  "(427,(432,436), p)",
"16" :  "(427,(432,438), p)",
"17" :  "(427,(432,440), p)",
"18" :  "(427,(432,447), p)",
"19" :  "(427,(432,449), p)",
"20" :  "(427,(432,454), p)",
"21" :  "(427,(432,444), p)",
"22" :  "(427,(432,457), p)",
"23" :  "(427,(432,459), p)",
"24" :  "(429,(432,461), p)",
"25" :  "(429,(432,434), p)",
"26" :  "(429,(432,436), p)",
"27" :  "(429,(432,438), p)",
"28" :  "(429,(432,440), p)",
"29" :  "(429,(432,447), p)",
"30" :  "(429,(432,449), p)",
"31" :  "(429,(432,454), p)",
"32" :  "(429,(432,444), p)",
"33" :  "(429,(432,457), p)",
"34" :  "(429,(432,459), p)"},{ "Name" : "doPeek" ,
"Duas" : 159,
"0" :  "(466,483, this)",
"1" :  "(466,498, this)",
"2" :  "(466,509, this)",
"3" :  "(466,507, this)",
"4" :  "(466,503, this)",
"5" :  "(466,504, this)",
"6" :  "(466,501, this)",
"7" :  "(466,512, this)",
"8" :  "(466,513, this)",
"9" :  "(466,(514,515), this)",
"10" :  "(466,(514,517), this)",
"11" :  "(466,517, this)",
"12" :  "(466,515, this)",
"13" :  "(466,486, this)",
"14" :  "(466,489, this)",
"15" :  "(466,491, this)",
"16" :  "(466,495, this)",
"17" :  "(466,553, this)",
"18" :  "(466,581, this)",
"19" :  "(466,557, this)",
"20" :  "(466,579, this)",
"21" :  "(466,564, this)",
"22" :  "(466,565, this)",
"23" :  "(466,566, this)",
"24" :  "(466,568, this)",
"25" :  "(466,571, this)",
"26" :  "(466,572, this)",
"27" :  "(466,(574,575), this)",
"28" :  "(466,(574,577), this)",
"29" :  "(466,577, this)",
"30" :  "(466,575, this)",
"31" :  "(466,583, this)",
"32" :  "(466,(585,586), this)",
"33" :  "(466,(585,589), this)",
"34" :  "(466,589, this)",
"35" :  "(466,594, this)",
"36" :  "(466,(599,600), this)",
"37" :  "(466,(599,603), this)",
"38" :  "(466,603, this)",
"39" :  "(466,604, this)",
"40" :  "(466,600, this)",
"41" :  "(466,586, this)",
"42" :  "(466,542, this)",
"43" :  "(466,546, this)",
"44" :  "(466,547, this)",
"45" :  "(466,544, this)",
"46" :  "(466,(537,538), this)",
"47" :  "(466,(537,540), this)",
"48" :  "(466,540, this)",
"49" :  "(466,538, this)",
"50" :  "(466,521, this)",
"51" :  "(466,523, this)",
"52" :  "(466,528, this)",
"53" :  "(466,(529,529), this)",
"54" :  "(466,(529,529), this)",
"55" :  "(466,(529,530), this)",
"56" :  "(466,(529,536), this)",
"57" :  "(466,530, this)",
"58" :  "(466,(529,529), this)",
"59" :  "(466,(529,536), this)",
"60" :  "(466,534, this)",
"61" :  "(466,471, this)",
"62" :  "(466,474, this)",
"63" :  "(466,476, this)",
"64" :  "(466,480, this)",
"65" :  "(466,468, this)",
"66" :  "(466,483, this.stack)",
"67" :  "(466,540, this.stack)",
"68" :  "(466,521, this.stack)",
"69" :  "(466,468, this.stack)",
"70" :  "(466,483, this.stackSize)",
"71" :  "(466,(574,575), this.stackSize)",
"72" :  "(466,(574,577), this.stackSize)",
"73" :  "(466,(585,586), this.stackSize)",
"74" :  "(466,(585,589), this.stackSize)",
"75" :  "(466,540, this.stackSize)",
"76" :  "(466,521, this.stackSize)",
"77" :  "(466,468, this.stackSize)",
"78" :  "(466,513, this.pos)",
"79" :  "(466,565, this.pos)",
"80" :  "(466,583, this.pos)",
"81" :  "(466,547, this.pos)",
"82" :  "(466,(529,529), this.pos)",
"83" :  "(466,(529,529), this.pos)",
"84" :  "(466,(529,530), this.pos)",
"85" :  "(466,(529,536), this.pos)",
"86" :  "(466,530, this.pos)",
"87" :  "(466,(529,529), this.limit)",
"88" :  "(466,(529,529), this.limit)",
"89" :  "(466,(599,600), this.buffer)",
"90" :  "(466,(599,603), this.buffer)",
"91" :  "(466,(529,530), this.buffer)",
"92" :  "(466,(529,536), this.buffer)",
"93" :  "(466,(537,538), this.lenient)",
"94" :  "(466,(537,540), this.lenient)",
"95" :  "(466,(467,468), peekStack)",
"96" :  "(466,(467,469), peekStack)",
"97" :  "(466,(469,471), peekStack)",
"98" :  "(466,(469,482), peekStack)",
"99" :  "(466,(482,482), peekStack)",
"100" :  "(466,(482,483), peekStack)",
"101" :  "(466,(485,486), peekStack)",
"102" :  "(466,(485,498), peekStack)",
"103" :  "(466,(506,507), peekStack)",
"104" :  "(466,(506,509), peekStack)",
"105" :  "(466,(482,483), peekStack)",
"106" :  "(466,(482,520), peekStack)",
"107" :  "(466,(520,521), peekStack)",
"108" :  "(466,(520,536), peekStack)",
"109" :  "(466,(536,537), peekStack)",
"110" :  "(466,(536,541), peekStack)",
"111" :  "(466,(541,542), peekStack)",
"112" :  "(466,(541,549), peekStack)",
"113" :  "(466,(549,550), peekStack)",
"114" :  "(466,(549,553), peekStack)",
"115" :  "(466,(556,557), peekStack)",
"116" :  "(466,(556,563), peekStack)",
"117" :  "(466,(563,563), peekStack)",
"118" :  "(466,(563,564), peekStack)",
"119" :  "(466,(563,564), peekStack)",
"120" :  "(466,(563,568), peekStack)",
"121" :  "(471,(472,480), c)",
"122" :  "(471,(472,478), c)",
"123" :  "(471,(472,476), c)",
"124" :  "(471,(472,474), c)",
"125" :  "(486,(487,495), c)",
"126" :  "(486,(487,493), c)",
"127" :  "(486,(487,491), c)",
"128" :  "(486,(487,489), c)",
"129" :  "(498,(499,512), c)",
"130" :  "(498,(499,501), c)",
"131" :  "(498,(499,503), c)",
"132" :  "(498,(499,506), c)",
"133" :  "(498,(514,515), c)",
"134" :  "(498,(514,517), c)",
"135" :  "(523,(524,534), c)",
"136" :  "(523,(524,526), c)",
"137" :  "(523,(524,528), c)",
"138" :  "(530,565, this.pos)",
"139" :  "(530,583, this.pos)",
"140" :  "(542,(543,544), c)",
"141" :  "(542,(543,546), c)",
"142" :  "(547,565, this.pos)",
"143" :  "(547,583, this.pos)",
"144" :  "(553,(554,583), c)",
"145" :  "(553,(554,574), c)",
"146" :  "(553,(554,571), c)",
"147" :  "(553,(554,563), c)",
"148" :  "(553,(554,579), c)",
"149" :  "(553,(554,556), c)",
"150" :  "(553,(554,581), c)",
"151" :  "(583,(599,600), this.pos)",
"152" :  "(583,(599,603), this.pos)",
"153" :  "(589,(590,591), result)",
"154" :  "(589,(590,594), result)",
"155" :  "(589,591, result)",
"156" :  "(594,(595,596), result)",
"157" :  "(594,(595,599), result)",
"158" :  "(594,596, result)"},{ "Name" : "peekKeyword" ,
"Duas" : 98,
"0" :  "(609,(641,641), this)",
"1" :  "(609,(641,641), this)",
"2" :  "(609,(641,643), this)",
"3" :  "(609,(641,647), this)",
"4" :  "(609,647, this)",
"5" :  "(609,648, this)",
"6" :  "(609,(641,641), this)",
"7" :  "(609,(641,647), this)",
"8" :  "(609,(632,632), this)",
"9" :  "(609,(632,635), this)",
"10" :  "(609,635, this)",
"11" :  "(609,(632,633), this)",
"12" :  "(609,(632,635), this)",
"13" :  "(609,(641,643), this.buffer)",
"14" :  "(609,(641,647), this.buffer)",
"15" :  "(609,635, this.buffer)",
"16" :  "(609,(641,641), this.pos)",
"17" :  "(609,(641,641), this.pos)",
"18" :  "(609,(641,643), this.pos)",
"19" :  "(609,(641,647), this.pos)",
"20" :  "(609,647, this.pos)",
"21" :  "(609,(632,632), this.pos)",
"22" :  "(609,(632,635), this.pos)",
"23" :  "(609,635, this.pos)",
"24" :  "(609,(641,641), this.limit)",
"25" :  "(609,(641,641), this.limit)",
"26" :  "(609,(632,632), this.limit)",
"27" :  "(609,(632,635), this.limit)",
"28" :  "(609,(613,613), c)",
"29" :  "(609,(613,614), c)",
"30" :  "(609,(613,614), c)",
"31" :  "(609,(613,617), c)",
"32" :  "(609,(617,617), c)",
"33" :  "(609,(617,618), c)",
"34" :  "(609,(617,618), c)",
"35" :  "(609,(617,621), c)",
"36" :  "(609,(621,621), c)",
"37" :  "(609,(621,622), c)",
"38" :  "(609,(621,622), c)",
"39" :  "(609,(621,626), c)",
"40" :  "(614,630, keyword)",
"41" :  "(614,(636,636), keyword)",
"42" :  "(614,(636,631), keyword)",
"43" :  "(615,(636,637), keywordUpper)",
"44" :  "(615,(636,631), keywordUpper)",
"45" :  "(616,648, peeking)",
"46" :  "(616,648, peeking)",
"47" :  "(618,630, keyword)",
"48" :  "(618,(636,636), keyword)",
"49" :  "(618,(636,631), keyword)",
"50" :  "(619,(636,637), keywordUpper)",
"51" :  "(619,(636,631), keywordUpper)",
"52" :  "(620,648, peeking)",
"53" :  "(620,648, peeking)",
"54" :  "(622,630, keyword)",
"55" :  "(622,(636,636), keyword)",
"56" :  "(622,(636,631), keyword)",
"57" :  "(623,(636,637), keywordUpper)",
"58" :  "(623,(636,631), keywordUpper)",
"59" :  "(624,648, peeking)",
"60" :  "(624,648, peeking)",
"61" :  "(630,(631,632), length)",
"62" :  "(630,(631,641), length)",
"63" :  "(630,(641,641), length)",
"64" :  "(630,(641,641), length)",
"65" :  "(630,(641,643), length)",
"66" :  "(630,(641,647), length)",
"67" :  "(630,647, length)",
"68" :  "(630,(641,641), length)",
"69" :  "(630,(641,647), length)",
"70" :  "(631,(631,632), i)",
"71" :  "(631,(631,641), i)",
"72" :  "(631,(632,632), i)",
"73" :  "(631,(632,635), i)",
"74" :  "(631,635, i)",
"75" :  "(631,(636,636), i)",
"76" :  "(631,(636,631), i)",
"77" :  "(631,631, i)",
"78" :  "(631,(636,637), i)",
"79" :  "(631,(636,631), i)",
"80" :  "(631,(632,633), i)",
"81" :  "(631,(632,635), i)",
"82" :  "(635,(636,636), c)",
"83" :  "(635,(636,631), c)",
"84" :  "(635,(636,637), c)",
"85" :  "(635,(636,631), c)",
"86" :  "(631,(631,632), i)",
"87" :  "(631,(631,641), i)",
"88" :  "(631,(632,632), i)",
"89" :  "(631,(632,635), i)",
"90" :  "(631,635, i)",
"91" :  "(631,(636,636), i)",
"92" :  "(631,(636,631), i)",
"93" :  "(631,631, i)",
"94" :  "(631,(636,637), i)",
"95" :  "(631,(636,631), i)",
"96" :  "(631,(632,633), i)",
"97" :  "(631,(632,635), i)"},{ "Name" : "peekNumber" ,
"Duas" : 401,
"0" :  "(653,(716,717), this)",
"1" :  "(653,(716,719), this)",
"2" :  "(653,747, this)",
"3" :  "(653,748, this)",
"4" :  "(653,742, this)",
"5" :  "(653,743, this)",
"6" :  "(653,744, this)",
"7" :  "(653,(672,673), this)",
"8" :  "(653,(672,675), this)",
"9" :  "(653,675, this)",
"10" :  "(653,676, this)",
"11" :  "(653,743, this.pos)",
"12" :  "(653,675, this.pos)",
"13" :  "(653,676, this.limit)",
"14" :  "(653,679, buffer)",
"15" :  "(653,(667,670), buffer)",
"16" :  "(653,(667,672), buffer)",
"17" :  "(654,(666,667), p)",
"18" :  "(654,(666,679), p)",
"19" :  "(654,679, p)",
"20" :  "(655,(666,667), l)",
"21" :  "(655,(666,679), l)",
"22" :  "(657,(741,741), value)",
"23" :  "(657,(741,742), value)",
"24" :  "(657,742, value)",
"25" :  "(657,(725,726), value)",
"26" :  "(657,(725,728), value)",
"27" :  "(657,728, value)",
"28" :  "(657,(729,729), value)",
"29" :  "(657,(729,729), value)",
"30" :  "(657,(729,729), value)",
"31" :  "(657,(729,729), value)",
"32" :  "(657,(729,729), value)",
"33" :  "(657,(729,729), value)",
"34" :  "(658,(742,742), negative)",
"35" :  "(658,(742,742), negative)",
"36" :  "(658,(741,742), negative)",
"37" :  "(658,(741,745), negative)",
"38" :  "(659,(741,741), fitsInLong)",
"39" :  "(659,(741,745), fitsInLong)",
"40" :  "(659,729, fitsInLong)",
"41" :  "(660,(701,701), last)",
"42" :  "(660,(701,702), last)",
"43" :  "(660,(701,702), last)",
"44" :  "(660,(701,705), last)",
"45" :  "(660,(708,709), last)",
"46" :  "(660,(708,712), last)",
"47" :  "(660,(682,683), last)",
"48" :  "(660,(682,686), last)",
"49" :  "(660,(686,687), last)",
"50" :  "(660,(686,690), last)",
"51" :  "(660,(693,694), last)",
"52" :  "(660,(693,697), last)",
"53" :  "(660,(741,741), last)",
"54" :  "(660,(741,745), last)",
"55" :  "(660,(745,745), last)",
"56" :  "(660,(745,747), last)",
"57" :  "(660,(745,745), last)",
"58" :  "(660,(745,747), last)",
"59" :  "(660,(745,747), last)",
"60" :  "(660,(745,750), last)",
"61" :  "(660,(721,721), last)",
"62" :  "(660,(721,722), last)",
"63" :  "(660,(721,722), last)",
"64" :  "(660,(721,724), last)",
"65" :  "(660,(724,725), last)",
"66" :  "(660,(724,732), last)",
"67" :  "(660,(732,733), last)",
"68" :  "(660,(732,734), last)",
"69" :  "(660,(734,734), last)",
"70" :  "(660,(734,735), last)",
"71" :  "(660,(734,735), last)",
"72" :  "(660,(734,665), last)",
"73" :  "(662,(666,667), i)",
"74" :  "(662,(666,679), i)",
"75" :  "(662,679, i)",
"76" :  "(662,665, i)",
"77" :  "(662,747, i)",
"78" :  "(662,743, i)",
"79" :  "(662,(667,670), i)",
"80" :  "(662,(667,672), i)",
"81" :  "(662,(672,673), i)",
"82" :  "(662,(672,675), i)",
"83" :  "(675,679, p)",
"84" :  "(675,(666,667), p)",
"85" :  "(675,(666,679), p)",
"86" :  "(676,(666,667), l)",
"87" :  "(676,(666,679), l)",
"88" :  "(679,(680,715), c)",
"89" :  "(679,(680,693), c)",
"90" :  "(679,(680,682), c)",
"91" :  "(679,(680,708), c)",
"92" :  "(679,(680,701), c)",
"93" :  "(679,(715,715), c)",
"94" :  "(679,(715,716), c)",
"95" :  "(679,(716,717), c)",
"96" :  "(679,(716,719), c)",
"97" :  "(679,(715,716), c)",
"98" :  "(679,(715,721), c)",
"99" :  "(679,722, c)",
"100" :  "(679,728, c)",
"101" :  "(683,(742,742), negative)",
"102" :  "(683,(742,742), negative)",
"103" :  "(683,(741,742), negative)",
"104" :  "(683,(741,745), negative)",
"105" :  "(684,(701,701), last)",
"106" :  "(684,(701,702), last)",
"107" :  "(684,(701,702), last)",
"108" :  "(684,(701,705), last)",
"109" :  "(684,(708,709), last)",
"110" :  "(684,(708,712), last)",
"111" :  "(684,(682,683), last)",
"112" :  "(684,(682,686), last)",
"113" :  "(684,(686,687), last)",
"114" :  "(684,(686,690), last)",
"115" :  "(684,(693,694), last)",
"116" :  "(684,(693,697), last)",
"117" :  "(684,(741,741), last)",
"118" :  "(684,(741,745), last)",
"119" :  "(684,(745,745), last)",
"120" :  "(684,(745,747), last)",
"121" :  "(684,(745,745), last)",
"122" :  "(684,(745,747), last)",
"123" :  "(684,(745,747), last)",
"124" :  "(684,(745,750), last)",
"125" :  "(684,(721,721), last)",
"126" :  "(684,(721,722), last)",
"127" :  "(684,(721,722), last)",
"128" :  "(684,(721,724), last)",
"129" :  "(684,(724,725), last)",
"130" :  "(684,(724,732), last)",
"131" :  "(684,(732,733), last)",
"132" :  "(684,(732,734), last)",
"133" :  "(684,(734,734), last)",
"134" :  "(684,(734,735), last)",
"135" :  "(684,(734,735), last)",
"136" :  "(684,(734,665), last)",
"137" :  "(687,(701,701), last)",
"138" :  "(687,(701,702), last)",
"139" :  "(687,(701,702), last)",
"140" :  "(687,(701,705), last)",
"141" :  "(687,(708,709), last)",
"142" :  "(687,(708,712), last)",
"143" :  "(687,(682,683), last)",
"144" :  "(687,(682,686), last)",
"145" :  "(687,(686,687), last)",
"146" :  "(687,(686,690), last)",
"147" :  "(687,(693,694), last)",
"148" :  "(687,(693,697), last)",
"149" :  "(687,(741,741), last)",
"150" :  "(687,(741,745), last)",
"151" :  "(687,(745,745), last)",
"152" :  "(687,(745,747), last)",
"153" :  "(687,(745,745), last)",
"154" :  "(687,(745,747), last)",
"155" :  "(687,(745,747), last)",
"156" :  "(687,(745,750), last)",
"157" :  "(687,(721,721), last)",
"158" :  "(687,(721,722), last)",
"159" :  "(687,(721,722), last)",
"160" :  "(687,(721,724), last)",
"161" :  "(687,(724,725), last)",
"162" :  "(687,(724,732), last)",
"163" :  "(687,(732,733), last)",
"164" :  "(687,(732,734), last)",
"165" :  "(687,(734,734), last)",
"166" :  "(687,(734,735), last)",
"167" :  "(687,(734,735), last)",
"168" :  "(687,(734,665), last)",
"169" :  "(694,(701,701), last)",
"170" :  "(694,(701,702), last)",
"171" :  "(694,(701,702), last)",
"172" :  "(694,(701,705), last)",
"173" :  "(694,(708,709), last)",
"174" :  "(694,(708,712), last)",
"175" :  "(694,(682,683), last)",
"176" :  "(694,(682,686), last)",
"177" :  "(694,(686,687), last)",
"178" :  "(694,(686,690), last)",
"179" :  "(694,(693,694), last)",
"180" :  "(694,(693,697), last)",
"181" :  "(694,(741,741), last)",
"182" :  "(694,(741,745), last)",
"183" :  "(694,(745,745), last)",
"184" :  "(694,(745,747), last)",
"185" :  "(694,(745,745), last)",
"186" :  "(694,(745,747), last)",
"187" :  "(694,(745,747), last)",
"188" :  "(694,(745,750), last)",
"189" :  "(694,(721,721), last)",
"190" :  "(694,(721,722), last)",
"191" :  "(694,(721,722), last)",
"192" :  "(694,(721,724), last)",
"193" :  "(694,(724,725), last)",
"194" :  "(694,(724,732), last)",
"195" :  "(694,(732,733), last)",
"196" :  "(694,(732,734), last)",
"197" :  "(694,(734,734), last)",
"198" :  "(694,(734,735), last)",
"199" :  "(694,(734,735), last)",
"200" :  "(694,(734,665), last)",
"201" :  "(702,(701,701), last)",
"202" :  "(702,(701,702), last)",
"203" :  "(702,(701,702), last)",
"204" :  "(702,(701,705), last)",
"205" :  "(702,(708,709), last)",
"206" :  "(702,(708,712), last)",
"207" :  "(702,(682,683), last)",
"208" :  "(702,(682,686), last)",
"209" :  "(702,(686,687), last)",
"210" :  "(702,(686,690), last)",
"211" :  "(702,(693,694), last)",
"212" :  "(702,(693,697), last)",
"213" :  "(702,(741,741), last)",
"214" :  "(702,(741,745), last)",
"215" :  "(702,(745,745), last)",
"216" :  "(702,(745,747), last)",
"217" :  "(702,(745,745), last)",
"218" :  "(702,(745,747), last)",
"219" :  "(702,(745,747), last)",
"220" :  "(702,(745,750), last)",
"221" :  "(702,(721,721), last)",
"222" :  "(702,(721,722), last)",
"223" :  "(702,(721,722), last)",
"224" :  "(702,(721,724), last)",
"225" :  "(702,(724,725), last)",
"226" :  "(702,(724,732), last)",
"227" :  "(702,(732,733), last)",
"228" :  "(702,(732,734), last)",
"229" :  "(702,(734,734), last)",
"230" :  "(702,(734,735), last)",
"231" :  "(702,(734,735), last)",
"232" :  "(702,(734,665), last)",
"233" :  "(709,(701,701), last)",
"234" :  "(709,(701,702), last)",
"235" :  "(709,(701,702), last)",
"236" :  "(709,(701,705), last)",
"237" :  "(709,(708,709), last)",
"238" :  "(709,(708,712), last)",
"239" :  "(709,(682,683), last)",
"240" :  "(709,(682,686), last)",
"241" :  "(709,(686,687), last)",
"242" :  "(709,(686,690), last)",
"243" :  "(709,(693,694), last)",
"244" :  "(709,(693,697), last)",
"245" :  "(709,(741,741), last)",
"246" :  "(709,(741,745), last)",
"247" :  "(709,(745,745), last)",
"248" :  "(709,(745,747), last)",
"249" :  "(709,(745,745), last)",
"250" :  "(709,(745,747), last)",
"251" :  "(709,(745,747), last)",
"252" :  "(709,(745,750), last)",
"253" :  "(709,(721,721), last)",
"254" :  "(709,(721,722), last)",
"255" :  "(709,(721,722), last)",
"256" :  "(709,(721,724), last)",
"257" :  "(709,(724,725), last)",
"258" :  "(709,(724,732), last)",
"259" :  "(709,(732,733), last)",
"260" :  "(709,(732,734), last)",
"261" :  "(709,(734,734), last)",
"262" :  "(709,(734,735), last)",
"263" :  "(709,(734,735), last)",
"264" :  "(709,(734,665), last)",
"265" :  "(722,(741,741), value)",
"266" :  "(722,(741,742), value)",
"267" :  "(722,742, value)",
"268" :  "(722,(725,726), value)",
"269" :  "(722,(725,728), value)",
"270" :  "(722,728, value)",
"271" :  "(722,(729,729), value)",
"272" :  "(722,(729,729), value)",
"273" :  "(722,(729,729), value)",
"274" :  "(722,(729,729), value)",
"275" :  "(722,(729,729), value)",
"276" :  "(722,(729,729), value)",
"277" :  "(723,(701,701), last)",
"278" :  "(723,(701,702), last)",
"279" :  "(723,(701,702), last)",
"280" :  "(723,(701,705), last)",
"281" :  "(723,(708,709), last)",
"282" :  "(723,(708,712), last)",
"283" :  "(723,(682,683), last)",
"284" :  "(723,(682,686), last)",
"285" :  "(723,(686,687), last)",
"286" :  "(723,(686,690), last)",
"287" :  "(723,(693,694), last)",
"288" :  "(723,(693,697), last)",
"289" :  "(723,(741,741), last)",
"290" :  "(723,(741,745), last)",
"291" :  "(723,(745,745), last)",
"292" :  "(723,(745,747), last)",
"293" :  "(723,(745,745), last)",
"294" :  "(723,(745,747), last)",
"295" :  "(723,(745,747), last)",
"296" :  "(723,(745,750), last)",
"297" :  "(723,(721,721), last)",
"298" :  "(723,(721,722), last)",
"299" :  "(723,(721,722), last)",
"300" :  "(723,(721,724), last)",
"301" :  "(723,(724,725), last)",
"302" :  "(723,(724,732), last)",
"303" :  "(723,(732,733), last)",
"304" :  "(723,(732,734), last)",
"305" :  "(723,(734,734), last)",
"306" :  "(723,(734,735), last)",
"307" :  "(723,(734,735), last)",
"308" :  "(723,(734,665), last)",
"309" :  "(728,731, newValue)",
"310" :  "(728,(729,729), newValue)",
"311" :  "(728,(729,729), newValue)",
"312" :  "(729,(741,741), fitsInLong)",
"313" :  "(729,(741,745), fitsInLong)",
"314" :  "(729,729, fitsInLong)",
"315" :  "(731,(741,741), value)",
"316" :  "(731,(741,742), value)",
"317" :  "(731,742, value)",
"318" :  "(731,(725,726), value)",
"319" :  "(731,(725,728), value)",
"320" :  "(731,728, value)",
"321" :  "(731,(729,729), value)",
"322" :  "(731,(729,729), value)",
"323" :  "(731,(729,729), value)",
"324" :  "(731,(729,729), value)",
"325" :  "(731,(729,729), value)",
"326" :  "(731,(729,729), value)",
"327" :  "(733,(701,701), last)",
"328" :  "(733,(701,702), last)",
"329" :  "(733,(701,702), last)",
"330" :  "(733,(701,705), last)",
"331" :  "(733,(708,709), last)",
"332" :  "(733,(708,712), last)",
"333" :  "(733,(682,683), last)",
"334" :  "(733,(682,686), last)",
"335" :  "(733,(686,687), last)",
"336" :  "(733,(686,690), last)",
"337" :  "(733,(693,694), last)",
"338" :  "(733,(693,697), last)",
"339" :  "(733,(741,741), last)",
"340" :  "(733,(741,745), last)",
"341" :  "(733,(745,745), last)",
"342" :  "(733,(745,747), last)",
"343" :  "(733,(745,745), last)",
"344" :  "(733,(745,747), last)",
"345" :  "(733,(745,747), last)",
"346" :  "(733,(745,750), last)",
"347" :  "(733,(721,721), last)",
"348" :  "(733,(721,722), last)",
"349" :  "(733,(721,722), last)",
"350" :  "(733,(721,724), last)",
"351" :  "(733,(724,725), last)",
"352" :  "(733,(724,732), last)",
"353" :  "(733,(732,733), last)",
"354" :  "(733,(732,734), last)",
"355" :  "(733,(734,734), last)",
"356" :  "(733,(734,735), last)",
"357" :  "(733,(734,735), last)",
"358" :  "(733,(734,665), last)",
"359" :  "(735,(701,701), last)",
"360" :  "(735,(701,702), last)",
"361" :  "(735,(701,702), last)",
"362" :  "(735,(701,705), last)",
"363" :  "(735,(708,709), last)",
"364" :  "(735,(708,712), last)",
"365" :  "(735,(682,683), last)",
"366" :  "(735,(682,686), last)",
"367" :  "(735,(686,687), last)",
"368" :  "(735,(686,690), last)",
"369" :  "(735,(693,694), last)",
"370" :  "(735,(693,697), last)",
"371" :  "(735,(741,741), last)",
"372" :  "(735,(741,745), last)",
"373" :  "(735,(745,745), last)",
"374" :  "(735,(745,747), last)",
"375" :  "(735,(745,745), last)",
"376" :  "(735,(745,747), last)",
"377" :  "(735,(745,747), last)",
"378" :  "(735,(745,750), last)",
"379" :  "(735,(721,721), last)",
"380" :  "(735,(721,722), last)",
"381" :  "(735,(721,722), last)",
"382" :  "(735,(721,724), last)",
"383" :  "(735,(724,725), last)",
"384" :  "(735,(724,732), last)",
"385" :  "(735,(732,733), last)",
"386" :  "(735,(732,734), last)",
"387" :  "(735,(734,734), last)",
"388" :  "(735,(734,735), last)",
"389" :  "(735,(734,735), last)",
"390" :  "(735,(734,665), last)",
"391" :  "(665,(666,667), i)",
"392" :  "(665,(666,679), i)",
"393" :  "(665,679, i)",
"394" :  "(665,665, i)",
"395" :  "(665,747, i)",
"396" :  "(665,743, i)",
"397" :  "(665,(667,670), i)",
"398" :  "(665,(667,672), i)",
"399" :  "(665,(672,673), i)",
"400" :  "(665,(672,675), i)"},{ "Name" : "isLiteral" ,
"Duas" : 4,
"0" :  "(755,761, this)",
"1" :  "(755,(755,775), c)",
"2" :  "(755,(755,773), c)",
"3" :  "(755,(755,761), c)"},{ "Name" : "nextName" ,
"Duas" : 29,
"0" :  "(787,799, this)",
"1" :  "(787,797, this)",
"2" :  "(787,802, this)",
"3" :  "(787,803, this)",
"4" :  "(787,795, this)",
"5" :  "(787,793, this)",
"6" :  "(787,789, this)",
"7" :  "(787,803, this.stackSize)",
"8" :  "(787,803, this.pathNames)",
"9" :  "(787,(788,789), p)",
"10" :  "(787,(788,792), p)",
"11" :  "(787,(792,793), p)",
"12" :  "(787,(792,794), p)",
"13" :  "(787,(794,795), p)",
"14" :  "(787,(794,796), p)",
"15" :  "(787,(796,797), p)",
"16" :  "(787,(796,799), p)",
"17" :  "(789,(792,793), p)",
"18" :  "(789,(792,794), p)",
"19" :  "(789,(794,795), p)",
"20" :  "(789,(794,796), p)",
"21" :  "(789,(796,797), p)",
"22" :  "(789,(796,799), p)",
"23" :  "(793,803, result)",
"24" :  "(793,804, result)",
"25" :  "(795,803, result)",
"26" :  "(795,804, result)",
"27" :  "(797,803, result)",
"28" :  "(797,804, result)"},{ "Name" : "nextString" ,
"Duas" : 53,
"0" :  "(816,836, this)",
"1" :  "(816,833, this)",
"2" :  "(816,834, this)",
"3" :  "(816,839, this)",
"4" :  "(816,840, this)",
"5" :  "(816,831, this)",
"6" :  "(816,828, this)",
"7" :  "(816,829, this)",
"8" :  "(816,826, this)",
"9" :  "(816,824, this)",
"10" :  "(816,822, this)",
"11" :  "(816,818, this)",
"12" :  "(816,828, this.peekedString)",
"13" :  "(816,831, this.peekedLong)",
"14" :  "(816,833, this.buffer)",
"15" :  "(816,833, this.pos)",
"16" :  "(816,834, this.pos)",
"17" :  "(816,833, this.peekedNumberLength)",
"18" :  "(816,834, this.peekedNumberLength)",
"19" :  "(816,840, this.pathIndices)",
"20" :  "(816,840, this.stackSize)",
"21" :  "(816,(817,818), p)",
"22" :  "(816,(817,821), p)",
"23" :  "(816,(821,822), p)",
"24" :  "(816,(821,823), p)",
"25" :  "(816,(823,824), p)",
"26" :  "(816,(823,825), p)",
"27" :  "(816,(825,826), p)",
"28" :  "(816,(825,827), p)",
"29" :  "(816,(827,828), p)",
"30" :  "(816,(827,830), p)",
"31" :  "(816,(830,831), p)",
"32" :  "(816,(830,832), p)",
"33" :  "(816,(832,833), p)",
"34" :  "(816,(832,836), p)",
"35" :  "(818,(821,822), p)",
"36" :  "(818,(821,823), p)",
"37" :  "(818,(823,824), p)",
"38" :  "(818,(823,825), p)",
"39" :  "(818,(825,826), p)",
"40" :  "(818,(825,827), p)",
"41" :  "(818,(827,828), p)",
"42" :  "(818,(827,830), p)",
"43" :  "(818,(830,831), p)",
"44" :  "(818,(830,832), p)",
"45" :  "(818,(832,833), p)",
"46" :  "(818,(832,836), p)",
"47" :  "(822,841, result)",
"48" :  "(824,841, result)",
"49" :  "(826,841, result)",
"50" :  "(828,841, result)",
"51" :  "(831,841, result)",
"52" :  "(833,841, result)"},{ "Name" : "nextBoolean" ,
"Duas" : 20,
"0" :  "(852,865, this)",
"1" :  "(852,861, this)",
"2" :  "(852,862, this)",
"3" :  "(852,857, this)",
"4" :  "(852,858, this)",
"5" :  "(852,854, this)",
"6" :  "(852,862, this.pathIndices)",
"7" :  "(852,858, this.pathIndices)",
"8" :  "(852,862, this.stackSize)",
"9" :  "(852,858, this.stackSize)",
"10" :  "(852,(853,854), p)",
"11" :  "(852,(853,856), p)",
"12" :  "(852,(856,857), p)",
"13" :  "(852,(856,860), p)",
"14" :  "(852,(860,861), p)",
"15" :  "(852,(860,865), p)",
"16" :  "(854,(856,857), p)",
"17" :  "(854,(856,860), p)",
"18" :  "(854,(860,861), p)",
"19" :  "(854,(860,865), p)"},{ "Name" : "nextNull" ,
"Duas" : 12,
"0" :  "(877,885, this)",
"1" :  "(877,882, this)",
"2" :  "(877,883, this)",
"3" :  "(877,879, this)",
"4" :  "(877,883, this.pathIndices)",
"5" :  "(877,883, this.stackSize)",
"6" :  "(877,(878,879), p)",
"7" :  "(877,(878,881), p)",
"8" :  "(877,(881,882), p)",
"9" :  "(877,(881,885), p)",
"10" :  "(879,(881,882), p)",
"11" :  "(879,(881,885), p)"},{ "Name" : "nextDouble" ,
"Duas" : 70,
"0" :  "(900,915, this)",
"1" :  "(900,923, this)",
"2" :  "(900,924, this)",
"3" :  "(900,(925,925), this)",
"4" :  "(900,(925,929), this)",
"5" :  "(900,929, this)",
"6" :  "(900,930, this)",
"7" :  "(900,931, this)",
"8" :  "(900,926, this)",
"9" :  "(900,919, this)",
"10" :  "(900,917, this)",
"11" :  "(900,912, this)",
"12" :  "(900,912, this)",
"13" :  "(900,913, this)",
"14" :  "(900,906, this)",
"15" :  "(900,907, this)",
"16" :  "(900,908, this)",
"17" :  "(900,902, this)",
"18" :  "(900,931, this.pathIndices)",
"19" :  "(900,907, this.pathIndices)",
"20" :  "(900,931, this.stackSize)",
"21" :  "(900,907, this.stackSize)",
"22" :  "(900,908, this.peekedLong)",
"23" :  "(900,912, this.buffer)",
"24" :  "(900,912, this.pos)",
"25" :  "(900,913, this.pos)",
"26" :  "(900,912, this.peekedNumberLength)",
"27" :  "(900,913, this.peekedNumberLength)",
"28" :  "(900,924, this.peekedString)",
"29" :  "(900,(925,925), this.lenient)",
"30" :  "(900,(925,929), this.lenient)",
"31" :  "(900,(901,902), p)",
"32" :  "(900,(901,905), p)",
"33" :  "(900,(905,906), p)",
"34" :  "(900,(905,911), p)",
"35" :  "(900,(911,912), p)",
"36" :  "(900,(911,914), p)",
"37" :  "(900,(914,914), p)",
"38" :  "(900,(914,915), p)",
"39" :  "(900,(915,915), p)",
"40" :  "(900,(915,915), p)",
"41" :  "(900,(914,915), p)",
"42" :  "(900,(914,916), p)",
"43" :  "(900,(916,917), p)",
"44" :  "(900,(916,918), p)",
"45" :  "(900,(918,919), p)",
"46" :  "(900,(918,923), p)",
"47" :  "(902,(905,906), p)",
"48" :  "(902,(905,911), p)",
"49" :  "(902,(911,912), p)",
"50" :  "(902,(911,914), p)",
"51" :  "(902,(914,914), p)",
"52" :  "(902,(914,915), p)",
"53" :  "(902,(915,915), p)",
"54" :  "(902,(915,915), p)",
"55" :  "(902,(914,915), p)",
"56" :  "(902,(914,916), p)",
"57" :  "(902,(916,917), p)",
"58" :  "(902,(916,918), p)",
"59" :  "(902,(918,919), p)",
"60" :  "(902,(918,923), p)",
"61" :  "(912,924, this.peekedString)",
"62" :  "(915,924, this.peekedString)",
"63" :  "(917,924, this.peekedString)",
"64" :  "(924,932, result)",
"65" :  "(924,(925,925), result)",
"66" :  "(924,(925,926), result)",
"67" :  "(924,926, result)",
"68" :  "(924,(925,926), result)",
"69" :  "(924,(925,929), result)"},{ "Name" : "nextLong" ,
"Duas" : 58,
"0" :  "(946,961, this)",
"1" :  "(946,963, this)",
"2" :  "(946,964, this)",
"3" :  "(946,965, this)",
"4" :  "(946,971, this)",
"5" :  "(946,958, this)",
"6" :  "(946,958, this)",
"7" :  "(946,959, this)",
"8" :  "(946,975, this)",
"9" :  "(946,976, this)",
"10" :  "(946,982, this)",
"11" :  "(946,983, this)",
"12" :  "(946,984, this)",
"13" :  "(946,979, this)",
"14" :  "(946,952, this)",
"15" :  "(946,953, this)",
"16" :  "(946,954, this)",
"17" :  "(946,948, this)",
"18" :  "(946,965, this.pathIndices)",
"19" :  "(946,984, this.pathIndices)",
"20" :  "(946,953, this.pathIndices)",
"21" :  "(946,965, this.stackSize)",
"22" :  "(946,984, this.stackSize)",
"23" :  "(946,953, this.stackSize)",
"24" :  "(946,954, this.peekedLong)",
"25" :  "(946,958, this.buffer)",
"26" :  "(946,958, this.pos)",
"27" :  "(946,959, this.pos)",
"28" :  "(946,958, this.peekedNumberLength)",
"29" :  "(946,959, this.peekedNumberLength)",
"30" :  "(946,(947,948), p)",
"31" :  "(946,(947,951), p)",
"32" :  "(946,(951,952), p)",
"33" :  "(946,(951,957), p)",
"34" :  "(946,(957,958), p)",
"35" :  "(946,(957,960), p)",
"36" :  "(946,(960,960), p)",
"37" :  "(946,(960,961), p)",
"38" :  "(946,(961,961), p)",
"39" :  "(946,(961,961), p)",
"40" :  "(946,(960,961), p)",
"41" :  "(946,(960,971), p)",
"42" :  "(948,(951,952), p)",
"43" :  "(948,(951,957), p)",
"44" :  "(948,(957,958), p)",
"45" :  "(948,(957,960), p)",
"46" :  "(948,(960,960), p)",
"47" :  "(948,(960,961), p)",
"48" :  "(948,(961,961), p)",
"49" :  "(948,(961,961), p)",
"50" :  "(948,(960,961), p)",
"51" :  "(948,(960,971), p)",
"52" :  "(958,979, this.peekedString)",
"53" :  "(976,(978,979), asDouble)",
"54" :  "(976,(978,982), asDouble)",
"55" :  "(977,(978,979), result)",
"56" :  "(977,(978,982), result)",
"57" :  "(977,985, result)"},{ "Name" : "nextQuotedValue" ,
"Duas" : 66,
"0" :  "(1000,1003, this)",
"1" :  "(1000,1004, this)",
"2" :  "(1000,1028, this)",
"3" :  "(1000,(1029,1030), this)",
"4" :  "(1000,(1029,1032), this)",
"5" :  "(1000,1030, this)",
"6" :  "(1000,1022, this)",
"7" :  "(1000,1023, this)",
"8" :  "(1000,1015, this)",
"9" :  "(1000,1017, this)",
"10" :  "(1000,1018, this)",
"11" :  "(1000,1019, this)",
"12" :  "(1000,1011, this)",
"13" :  "(1000,(1010,1011), quote)",
"14" :  "(1000,(1010,1014), quote)",
"15" :  "(1000,1003, this.pos)",
"16" :  "(1000,1004, this.limit)",
"17" :  "(1000,1019, this.limit)",
"18" :  "(1000,1022, this.lineNumber)",
"19" :  "(1000,1027, buffer)",
"20" :  "(1000,1008, buffer)",
"21" :  "(1000,1016, buffer)",
"22" :  "(1000,1012, buffer)",
"23" :  "(1001,1027, builder)",
"24" :  "(1001,1016, builder)",
"25" :  "(1001,1017, builder)",
"26" :  "(1001,1012, builder)",
"27" :  "(1001,1013, builder)",
"28" :  "(1003,(1007,1008), p)",
"29" :  "(1003,(1007,1027), p)",
"30" :  "(1003,1027, p)",
"31" :  "(1003,1028, p)",
"32" :  "(1003,1008, p)",
"33" :  "(1004,(1007,1008), l)",
"34" :  "(1004,(1007,1027), l)",
"35" :  "(1006,1027, start)",
"36" :  "(1006,1016, start)",
"37" :  "(1006,1012, start)",
"38" :  "(1008,(1007,1008), p)",
"39" :  "(1008,(1007,1027), p)",
"40" :  "(1008,1027, p)",
"41" :  "(1008,1028, p)",
"42" :  "(1008,1008, p)",
"43" :  "(1008,1023, p)",
"44" :  "(1008,1015, p)",
"45" :  "(1008,1016, p)",
"46" :  "(1008,1011, p)",
"47" :  "(1008,1012, p)",
"48" :  "(1008,(1010,1011), c)",
"49" :  "(1008,(1010,1014), c)",
"50" :  "(1008,(1014,1015), c)",
"51" :  "(1008,(1014,1021), c)",
"52" :  "(1008,(1021,1022), c)",
"53" :  "(1008,(1021,1025), c)",
"54" :  "(1018,(1007,1008), p)",
"55" :  "(1018,(1007,1027), p)",
"56" :  "(1018,1027, p)",
"57" :  "(1018,1028, p)",
"58" :  "(1018,1008, p)",
"59" :  "(1019,(1007,1008), l)",
"60" :  "(1019,(1007,1027), l)",
"61" :  "(1020,1027, start)",
"62" :  "(1020,1016, start)",
"63" :  "(1020,1012, start)",
"64" :  "(1022,1022, this.lineNumber)",
"65" :  "(1028,1003, this.pos)"},{ "Name" : "nextUnquotedValue" ,
"Duas" : 108,
"0" :  "(1040,(1045,1046), this)",
"1" :  "(1040,(1045,1069), this)",
"2" :  "(1040,(1069,1070), this)",
"3" :  "(1040,(1069,1078), this)",
"4" :  "(1040,1081, this)",
"5" :  "(1040,1082, this)",
"6" :  "(1040,(1084,1085), this)",
"7" :  "(1040,(1084,1045), this)",
"8" :  "(1040,1093, this)",
"9" :  "(1040,1096, this)",
"10" :  "(1040,1091, this)",
"11" :  "(1040,(1070,1071), this)",
"12" :  "(1040,(1070,1090), this)",
"13" :  "(1040,(1046,1045), this)",
"14" :  "(1040,(1046,1064), this)",
"15" :  "(1040,(1046,1052), this)",
"16" :  "(1040,1052, this)",
"17" :  "(1040,(1045,1046), this.limit)",
"18" :  "(1040,(1045,1069), this.limit)",
"19" :  "(1040,(1045,1046), this.pos)",
"20" :  "(1040,(1045,1069), this.pos)",
"21" :  "(1040,1081, this.pos)",
"22" :  "(1040,1082, this.pos)",
"23" :  "(1040,1093, this.pos)",
"24" :  "(1040,1096, this.pos)",
"25" :  "(1040,1091, this.pos)",
"26" :  "(1040,(1046,1045), this.pos)",
"27" :  "(1040,(1046,1064), this.pos)",
"28" :  "(1040,(1046,1052), this.pos)",
"29" :  "(1040,(1069,1070), this.buffer)",
"30" :  "(1040,(1069,1078), this.buffer)",
"31" :  "(1040,1081, this.buffer)",
"32" :  "(1040,1093, this.buffer)",
"33" :  "(1040,1091, this.buffer)",
"34" :  "(1040,(1046,1045), this.buffer)",
"35" :  "(1040,(1046,1064), this.buffer)",
"36" :  "(1040,(1046,1052), this.buffer)",
"37" :  "(1040,(1078,1079), builder)",
"38" :  "(1040,(1078,1081), builder)",
"39" :  "(1040,1081, builder)",
"40" :  "(1040,(1090,1091), builder)",
"41" :  "(1040,(1090,1093), builder)",
"42" :  "(1040,1093, builder)",
"43" :  "(1040,1094, builder)",
"44" :  "(1041,(1045,1046), i)",
"45" :  "(1041,(1045,1069), i)",
"46" :  "(1041,(1069,1070), i)",
"47" :  "(1041,(1069,1078), i)",
"48" :  "(1041,1081, i)",
"49" :  "(1041,1082, i)",
"50" :  "(1041,(1070,1071), i)",
"51" :  "(1041,(1070,1090), i)",
"52" :  "(1041,1093, i)",
"53" :  "(1041,1096, i)",
"54" :  "(1041,1091, i)",
"55" :  "(1041,(1046,1045), i)",
"56" :  "(1041,(1046,1064), i)",
"57" :  "(1041,(1046,1052), i)",
"58" :  "(1041,1045, i)",
"59" :  "(1045,(1045,1046), i)",
"60" :  "(1045,(1045,1069), i)",
"61" :  "(1045,(1069,1070), i)",
"62" :  "(1045,(1069,1078), i)",
"63" :  "(1045,1081, i)",
"64" :  "(1045,1082, i)",
"65" :  "(1045,(1070,1071), i)",
"66" :  "(1045,(1070,1090), i)",
"67" :  "(1045,1093, i)",
"68" :  "(1045,1096, i)",
"69" :  "(1045,1091, i)",
"70" :  "(1045,(1046,1045), i)",
"71" :  "(1045,(1046,1064), i)",
"72" :  "(1045,(1046,1052), i)",
"73" :  "(1045,1045, i)",
"74" :  "(1079,1081, builder)",
"75" :  "(1079,(1078,1079), builder)",
"76" :  "(1079,(1078,1081), builder)",
"77" :  "(1079,(1090,1091), builder)",
"78" :  "(1079,(1090,1093), builder)",
"79" :  "(1079,1093, builder)",
"80" :  "(1079,1094, builder)",
"81" :  "(1082,(1045,1046), this.pos)",
"82" :  "(1082,(1045,1069), this.pos)",
"83" :  "(1082,1081, this.pos)",
"84" :  "(1082,1082, this.pos)",
"85" :  "(1082,1093, this.pos)",
"86" :  "(1082,1096, this.pos)",
"87" :  "(1082,1091, this.pos)",
"88" :  "(1082,(1046,1045), this.pos)",
"89" :  "(1082,(1046,1064), this.pos)",
"90" :  "(1082,(1046,1052), this.pos)",
"91" :  "(1083,(1045,1046), i)",
"92" :  "(1083,(1045,1069), i)",
"93" :  "(1083,(1069,1070), i)",
"94" :  "(1083,(1069,1078), i)",
"95" :  "(1083,1081, i)",
"96" :  "(1083,1082, i)",
"97" :  "(1083,(1070,1071), i)",
"98" :  "(1083,(1070,1090), i)",
"99" :  "(1083,1093, i)",
"100" :  "(1083,1096, i)",
"101" :  "(1083,1091, i)",
"102" :  "(1083,(1046,1045), i)",
"103" :  "(1083,(1046,1064), i)",
"104" :  "(1083,(1046,1052), i)",
"105" :  "(1083,1045, i)",
"106" :  "(1091,1097, result)",
"107" :  "(1094,1097, result)"},{ "Name" : "skipQuotedValue" ,
"Duas" : 47,
"0" :  "(1102,1104, this)",
"1" :  "(1102,1105, this)",
"2" :  "(1102,1122, this)",
"3" :  "(1102,(1123,1124), this)",
"4" :  "(1102,(1123,1104), this)",
"5" :  "(1102,1124, this)",
"6" :  "(1102,1118, this)",
"7" :  "(1102,1119, this)",
"8" :  "(1102,1113, this)",
"9" :  "(1102,1114, this)",
"10" :  "(1102,1115, this)",
"11" :  "(1102,1116, this)",
"12" :  "(1102,1110, this)",
"13" :  "(1102,(1109,1110), quote)",
"14" :  "(1102,(1109,1112), quote)",
"15" :  "(1102,1104, this.pos)",
"16" :  "(1102,1105, this.limit)",
"17" :  "(1102,1116, this.limit)",
"18" :  "(1102,1118, this.lineNumber)",
"19" :  "(1102,1108, buffer)",
"20" :  "(1104,(1107,1108), p)",
"21" :  "(1104,(1107,1122), p)",
"22" :  "(1104,1122, p)",
"23" :  "(1104,1108, p)",
"24" :  "(1105,(1107,1108), l)",
"25" :  "(1105,(1107,1122), l)",
"26" :  "(1108,(1107,1108), p)",
"27" :  "(1108,(1107,1122), p)",
"28" :  "(1108,1122, p)",
"29" :  "(1108,1108, p)",
"30" :  "(1108,1119, p)",
"31" :  "(1108,1113, p)",
"32" :  "(1108,1110, p)",
"33" :  "(1108,(1109,1110), c)",
"34" :  "(1108,(1109,1112), c)",
"35" :  "(1108,(1112,1113), c)",
"36" :  "(1108,(1112,1117), c)",
"37" :  "(1108,(1117,1118), c)",
"38" :  "(1108,(1117,1121), c)",
"39" :  "(1115,(1107,1108), p)",
"40" :  "(1115,(1107,1122), p)",
"41" :  "(1115,1122, p)",
"42" :  "(1115,1108, p)",
"43" :  "(1116,(1107,1108), l)",
"44" :  "(1116,(1107,1122), l)",
"45" :  "(1118,1118, this.lineNumber)",
"46" :  "(1122,1104, this.pos)"},{ "Name" : "skipUnquotedValue" ,
"Duas" : 38,
"0" :  "(1129,(1130,1131), this)",
"1" :  "(1129,(1130,1153), this)",
"2" :  "(1129,1153, this)",
"3" :  "(1129,(1154,1155), this)",
"4" :  "(1129,(1154,1129), this)",
"5" :  "(1129,(1131,1130), this)",
"6" :  "(1129,(1131,1149), this)",
"7" :  "(1129,(1131,1137), this)",
"8" :  "(1129,1137, this)",
"9" :  "(1129,1149, this)",
"10" :  "(1129,(1130,1131), this.limit)",
"11" :  "(1129,(1130,1153), this.limit)",
"12" :  "(1129,(1130,1131), this.pos)",
"13" :  "(1129,(1130,1153), this.pos)",
"14" :  "(1129,1153, this.pos)",
"15" :  "(1129,(1131,1130), this.pos)",
"16" :  "(1129,(1131,1149), this.pos)",
"17" :  "(1129,(1131,1137), this.pos)",
"18" :  "(1129,1149, this.pos)",
"19" :  "(1129,(1131,1130), this.buffer)",
"20" :  "(1129,(1131,1149), this.buffer)",
"21" :  "(1129,(1131,1137), this.buffer)",
"22" :  "(1129,(1130,1131), i)",
"23" :  "(1129,(1130,1153), i)",
"24" :  "(1129,1153, i)",
"25" :  "(1129,(1131,1130), i)",
"26" :  "(1129,(1131,1149), i)",
"27" :  "(1129,(1131,1137), i)",
"28" :  "(1129,1149, i)",
"29" :  "(1129,1130, i)",
"30" :  "(1130,(1130,1131), i)",
"31" :  "(1130,(1130,1153), i)",
"32" :  "(1130,1153, i)",
"33" :  "(1130,(1131,1130), i)",
"34" :  "(1130,(1131,1149), i)",
"35" :  "(1130,(1131,1137), i)",
"36" :  "(1130,1149, i)",
"37" :  "(1130,1130, i)"},{ "Name" : "nextInt" ,
"Duas" : 67,
"0" :  "(1168,1189, this)",
"1" :  "(1168,1191, this)",
"2" :  "(1168,1192, this)",
"3" :  "(1168,1193, this)",
"4" :  "(1168,1199, this)",
"5" :  "(1168,1186, this)",
"6" :  "(1168,1186, this)",
"7" :  "(1168,1187, this)",
"8" :  "(1168,1203, this)",
"9" :  "(1168,1204, this)",
"10" :  "(1168,1210, this)",
"11" :  "(1168,1211, this)",
"12" :  "(1168,1212, this)",
"13" :  "(1168,1207, this)",
"14" :  "(1168,1175, this)",
"15" :  "(1168,(1176,1177), this)",
"16" :  "(1168,(1176,1180), this)",
"17" :  "(1168,1180, this)",
"18" :  "(1168,1181, this)",
"19" :  "(1168,1177, this)",
"20" :  "(1168,1170, this)",
"21" :  "(1168,1175, this.peekedLong)",
"22" :  "(1168,(1176,1177), this.peekedLong)",
"23" :  "(1168,(1176,1180), this.peekedLong)",
"24" :  "(1168,1177, this.peekedLong)",
"25" :  "(1168,1193, this.pathIndices)",
"26" :  "(1168,1212, this.pathIndices)",
"27" :  "(1168,1181, this.pathIndices)",
"28" :  "(1168,1193, this.stackSize)",
"29" :  "(1168,1212, this.stackSize)",
"30" :  "(1168,1181, this.stackSize)",
"31" :  "(1168,1186, this.buffer)",
"32" :  "(1168,1186, this.pos)",
"33" :  "(1168,1187, this.pos)",
"34" :  "(1168,1186, this.peekedNumberLength)",
"35" :  "(1168,1187, this.peekedNumberLength)",
"36" :  "(1168,(1169,1170), p)",
"37" :  "(1168,(1169,1174), p)",
"38" :  "(1168,(1174,1175), p)",
"39" :  "(1168,(1174,1185), p)",
"40" :  "(1168,(1185,1186), p)",
"41" :  "(1168,(1185,1188), p)",
"42" :  "(1168,(1188,1188), p)",
"43" :  "(1168,(1188,1189), p)",
"44" :  "(1168,(1189,1189), p)",
"45" :  "(1168,(1189,1189), p)",
"46" :  "(1168,(1188,1189), p)",
"47" :  "(1168,(1188,1199), p)",
"48" :  "(1170,(1174,1175), p)",
"49" :  "(1170,(1174,1185), p)",
"50" :  "(1170,(1185,1186), p)",
"51" :  "(1170,(1185,1188), p)",
"52" :  "(1170,(1188,1188), p)",
"53" :  "(1170,(1188,1189), p)",
"54" :  "(1170,(1189,1189), p)",
"55" :  "(1170,(1189,1189), p)",
"56" :  "(1170,(1188,1189), p)",
"57" :  "(1170,(1188,1199), p)",
"58" :  "(1175,(1176,1177), result)",
"59" :  "(1175,(1176,1180), result)",
"60" :  "(1175,1182, result)",
"61" :  "(1186,1207, this.peekedString)",
"62" :  "(1204,(1206,1207), asDouble)",
"63" :  "(1204,(1206,1210), asDouble)",
"64" :  "(1205,(1206,1207), result)",
"65" :  "(1205,(1206,1210), result)",
"66" :  "(1205,1213, result)"},{ "Name" : "skipValue" ,
"Duas" : 108,
"0" :  "(1232,1234, this)",
"1" :  "(1232,1252, this)",
"2" :  "(1232,1260, this)",
"3" :  "(1232,1263, this)",
"4" :  "(1232,1264, this)",
"5" :  "(1232,1254, this)",
"6" :  "(1232,1256, this)",
"7" :  "(1232,1258, this)",
"8" :  "(1232,1249, this)",
"9" :  "(1232,1246, this)",
"10" :  "(1232,1243, this)",
"11" :  "(1232,1240, this)",
"12" :  "(1232,1236, this)",
"13" :  "(1232,1234, this.peeked)",
"14" :  "(1232,1263, this.stackSize)",
"15" :  "(1232,1264, this.stackSize)",
"16" :  "(1232,1249, this.stackSize)",
"17" :  "(1232,1246, this.stackSize)",
"18" :  "(1232,1258, this.pos)",
"19" :  "(1232,1258, this.peekedNumberLength)",
"20" :  "(1232,1263, this.pathIndices)",
"21" :  "(1232,1264, this.pathNames)",
"22" :  "(1232,(1261,1263), count)",
"23" :  "(1232,(1261,1234), count)",
"24" :  "(1232,1250, count)",
"25" :  "(1232,1247, count)",
"26" :  "(1232,1244, count)",
"27" :  "(1232,1241, count)",
"28" :  "(1234,(1235,1236), p)",
"29" :  "(1234,(1235,1239), p)",
"30" :  "(1234,(1239,1240), p)",
"31" :  "(1234,(1239,1242), p)",
"32" :  "(1234,(1242,1243), p)",
"33" :  "(1234,(1242,1245), p)",
"34" :  "(1234,(1245,1246), p)",
"35" :  "(1234,(1245,1248), p)",
"36" :  "(1234,(1248,1249), p)",
"37" :  "(1234,(1248,1251), p)",
"38" :  "(1234,(1251,1251), p)",
"39" :  "(1234,(1251,1252), p)",
"40" :  "(1234,(1251,1252), p)",
"41" :  "(1234,(1251,1253), p)",
"42" :  "(1234,(1253,1253), p)",
"43" :  "(1234,(1253,1254), p)",
"44" :  "(1234,(1253,1254), p)",
"45" :  "(1234,(1253,1255), p)",
"46" :  "(1234,(1255,1255), p)",
"47" :  "(1234,(1255,1256), p)",
"48" :  "(1234,(1255,1256), p)",
"49" :  "(1234,(1255,1257), p)",
"50" :  "(1234,(1257,1258), p)",
"51" :  "(1234,(1257,1260), p)",
"52" :  "(1236,(1239,1240), p)",
"53" :  "(1236,(1239,1242), p)",
"54" :  "(1236,(1242,1243), p)",
"55" :  "(1236,(1242,1245), p)",
"56" :  "(1236,(1245,1246), p)",
"57" :  "(1236,(1245,1248), p)",
"58" :  "(1236,(1248,1249), p)",
"59" :  "(1236,(1248,1251), p)",
"60" :  "(1236,(1251,1251), p)",
"61" :  "(1236,(1251,1252), p)",
"62" :  "(1236,(1251,1252), p)",
"63" :  "(1236,(1251,1253), p)",
"64" :  "(1236,(1253,1253), p)",
"65" :  "(1236,(1253,1254), p)",
"66" :  "(1236,(1253,1254), p)",
"67" :  "(1236,(1253,1255), p)",
"68" :  "(1236,(1255,1255), p)",
"69" :  "(1236,(1255,1256), p)",
"70" :  "(1236,(1255,1256), p)",
"71" :  "(1236,(1255,1257), p)",
"72" :  "(1236,(1257,1258), p)",
"73" :  "(1236,(1257,1260), p)",
"74" :  "(1241,(1261,1263), count)",
"75" :  "(1241,(1261,1234), count)",
"76" :  "(1241,1250, count)",
"77" :  "(1241,1247, count)",
"78" :  "(1241,1244, count)",
"79" :  "(1241,1241, count)",
"80" :  "(1244,(1261,1263), count)",
"81" :  "(1244,(1261,1234), count)",
"82" :  "(1244,1250, count)",
"83" :  "(1244,1247, count)",
"84" :  "(1244,1244, count)",
"85" :  "(1244,1241, count)",
"86" :  "(1246,1249, this.stackSize)",
"87" :  "(1246,1246, this.stackSize)",
"88" :  "(1246,1263, this.stackSize)",
"89" :  "(1246,1264, this.stackSize)",
"90" :  "(1247,(1261,1263), count)",
"91" :  "(1247,(1261,1234), count)",
"92" :  "(1247,1250, count)",
"93" :  "(1247,1247, count)",
"94" :  "(1247,1244, count)",
"95" :  "(1247,1241, count)",
"96" :  "(1249,1249, this.stackSize)",
"97" :  "(1249,1246, this.stackSize)",
"98" :  "(1249,1263, this.stackSize)",
"99" :  "(1249,1264, this.stackSize)",
"100" :  "(1250,(1261,1263), count)",
"101" :  "(1250,(1261,1234), count)",
"102" :  "(1250,1250, count)",
"103" :  "(1250,1247, count)",
"104" :  "(1250,1244, count)",
"105" :  "(1250,1241, count)",
"106" :  "(1258,1258, this.pos)",
"107" :  "(1260,1234, this.peeked)"},{ "Name" : "push" ,
"Duas" : 30,
"0" :  "(1268,(1268,1269), this)",
"1" :  "(1268,(1268,1279), this)",
"2" :  "(1268,1279, this)",
"3" :  "(1268,1279, this)",
"4" :  "(1268,1269, this)",
"5" :  "(1268,1270, this)",
"6" :  "(1268,1271, this)",
"7" :  "(1268,1272, this)",
"8" :  "(1268,1273, this)",
"9" :  "(1268,1274, this)",
"10" :  "(1268,1275, this)",
"11" :  "(1268,1276, this)",
"12" :  "(1268,1277, this)",
"13" :  "(1268,1279, newTop)",
"14" :  "(1268,(1268,1269), this.stack)",
"15" :  "(1268,(1268,1279), this.stack)",
"16" :  "(1268,1279, this.stack)",
"17" :  "(1268,1272, this.stack)",
"18" :  "(1268,(1268,1269), this.stackSize)",
"19" :  "(1268,(1268,1279), this.stackSize)",
"20" :  "(1268,1279, this.stackSize)",
"21" :  "(1268,1269, this.stackSize)",
"22" :  "(1268,1270, this.stackSize)",
"23" :  "(1268,1271, this.stackSize)",
"24" :  "(1268,1272, this.stackSize)",
"25" :  "(1268,1273, this.stackSize)",
"26" :  "(1268,1274, this.stackSize)",
"27" :  "(1268,1273, this.pathIndices)",
"28" :  "(1268,1274, this.pathNames)",
"29" :  "(1275,1279, this.stack)"},{ "Name" : "fillBuffer" ,
"Duas" : 69,
"0" :  "(1288,(1290,1291), this)",
"1" :  "(1288,(1290,1294), this)",
"2" :  "(1288,1294, this)",
"3" :  "(1288,1297, this)",
"4" :  "(1288,1299, this)",
"5" :  "(1288,(1299,1300), this)",
"6" :  "(1288,(1299,1313), this)",
"7" :  "(1288,1300, this)",
"8" :  "(1288,(1303,1303), this)",
"9" :  "(1288,(1303,1309), this)",
"10" :  "(1288,(1309,1310), this)",
"11" :  "(1288,(1309,1299), this)",
"12" :  "(1288,(1303,1303), this)",
"13" :  "(1288,(1303,1309), this)",
"14" :  "(1288,(1303,1303), this)",
"15" :  "(1288,(1303,1309), this)",
"16" :  "(1288,1304, this)",
"17" :  "(1288,1305, this)",
"18" :  "(1288,1291, this)",
"19" :  "(1288,1292, this)",
"20" :  "(1288,(1309,1310), minimum)",
"21" :  "(1288,(1309,1299), minimum)",
"22" :  "(1288,1306, minimum)",
"23" :  "(1288,(1290,1291), this.pos)",
"24" :  "(1288,(1290,1294), this.pos)",
"25" :  "(1288,1291, this.pos)",
"26" :  "(1288,1292, this.pos)",
"27" :  "(1288,(1290,1291), this.limit)",
"28" :  "(1288,(1290,1294), this.limit)",
"29" :  "(1288,1291, this.limit)",
"30" :  "(1288,1299, this.in)",
"31" :  "(1288,(1299,1300), this.in)",
"32" :  "(1288,(1299,1313), this.in)",
"33" :  "(1288,(1303,1303), this.lineNumber)",
"34" :  "(1288,(1303,1309), this.lineNumber)",
"35" :  "(1288,1299, buffer)",
"36" :  "(1288,(1299,1300), buffer)",
"37" :  "(1288,(1299,1313), buffer)",
"38" :  "(1288,(1303,1304), buffer)",
"39" :  "(1288,(1303,1309), buffer)",
"40" :  "(1288,1292, buffer)",
"41" :  "(1289,(1303,1303), this.lineStart)",
"42" :  "(1289,(1303,1309), this.lineStart)",
"43" :  "(1289,1305, this.lineStart)",
"44" :  "(1291,1299, this.limit)",
"45" :  "(1291,(1299,1300), this.limit)",
"46" :  "(1291,(1299,1313), this.limit)",
"47" :  "(1291,1300, this.limit)",
"48" :  "(1294,1299, this.limit)",
"49" :  "(1294,(1299,1300), this.limit)",
"50" :  "(1294,(1299,1313), this.limit)",
"51" :  "(1294,1300, this.limit)",
"52" :  "(1297,1304, this.pos)",
"53" :  "(1299,1300, total)",
"54" :  "(1300,(1309,1310), this.limit)",
"55" :  "(1300,(1309,1299), this.limit)",
"56" :  "(1300,1299, this.limit)",
"57" :  "(1300,(1299,1300), this.limit)",
"58" :  "(1300,(1299,1313), this.limit)",
"59" :  "(1300,1300, this.limit)",
"60" :  "(1300,(1303,1303), this.limit)",
"61" :  "(1300,(1303,1309), this.limit)",
"62" :  "(1304,1304, this.pos)",
"63" :  "(1305,(1303,1303), this.lineStart)",
"64" :  "(1305,(1303,1309), this.lineStart)",
"65" :  "(1305,1305, this.lineStart)",
"66" :  "(1306,(1309,1310), minimum)",
"67" :  "(1306,(1309,1299), minimum)",
"68" :  "(1306,1306, minimum)"},{ "Name" : "nextNonWhitespace" ,
"Duas" : 116,
"0" :  "(1339,1408, this)",
"1" :  "(1339,1397, this)",
"2" :  "(1339,1403, this)",
"3" :  "(1339,1404, this)",
"4" :  "(1339,1405, this)",
"5" :  "(1339,1406, this)",
"6" :  "(1339,1362, this)",
"7" :  "(1339,1372, this)",
"8" :  "(1339,1373, this)",
"9" :  "(1339,1387, this)",
"10" :  "(1339,1388, this)",
"11" :  "(1339,1389, this)",
"12" :  "(1339,1390, this)",
"13" :  "(1339,1377, this)",
"14" :  "(1339,(1378,1379), this)",
"15" :  "(1339,(1378,1381), this)",
"16" :  "(1339,1381, this)",
"17" :  "(1339,1382, this)",
"18" :  "(1339,1379, this)",
"19" :  "(1339,1364, this)",
"20" :  "(1339,1365, this)",
"21" :  "(1339,1366, this)",
"22" :  "(1339,1354, this)",
"23" :  "(1339,1355, this)",
"24" :  "(1339,1344, this)",
"25" :  "(1339,(1345,1346), this)",
"26" :  "(1339,(1345,1348), this)",
"27" :  "(1339,1348, this)",
"28" :  "(1339,1349, this)",
"29" :  "(1339,1413, this)",
"30" :  "(1339,(1412,1413), throwOnEof)",
"31" :  "(1339,(1412,1416), throwOnEof)",
"32" :  "(1339,1406, this.limit)",
"33" :  "(1339,1390, this.limit)",
"34" :  "(1339,1382, this.limit)",
"35" :  "(1339,1349, this.limit)",
"36" :  "(1339,1354, this.lineNumber)",
"37" :  "(1339,1352, buffer)",
"38" :  "(1339,1373, buffer)",
"39" :  "(1340,(1343,1344), p)",
"40" :  "(1340,(1343,1352), p)",
"41" :  "(1340,1352, p)",
"42" :  "(1340,1344, p)",
"43" :  "(1341,(1343,1344), l)",
"44" :  "(1341,(1343,1352), l)",
"45" :  "(1341,(1363,1364), l)",
"46" :  "(1341,(1363,1372), l)",
"47" :  "(1344,1348, this.pos)",
"48" :  "(1348,1352, p)",
"49" :  "(1349,(1343,1344), l)",
"50" :  "(1349,(1343,1352), l)",
"51" :  "(1349,(1363,1364), l)",
"52" :  "(1349,(1363,1372), l)",
"53" :  "(1352,(1343,1344), p)",
"54" :  "(1352,(1343,1352), p)",
"55" :  "(1352,1352, p)",
"56" :  "(1352,1344, p)",
"57" :  "(1352,1408, p)",
"58" :  "(1352,1397, p)",
"59" :  "(1352,1362, p)",
"60" :  "(1352,(1363,1364), p)",
"61" :  "(1352,(1363,1372), p)",
"62" :  "(1352,1355, p)",
"63" :  "(1352,(1353,1354), c)",
"64" :  "(1352,(1353,1357), c)",
"65" :  "(1352,(1357,1357), c)",
"66" :  "(1352,(1357,1343), c)",
"67" :  "(1352,(1357,1357), c)",
"68" :  "(1352,(1357,1343), c)",
"69" :  "(1352,(1357,1358), c)",
"70" :  "(1352,(1357,1361), c)",
"71" :  "(1352,(1361,1362), c)",
"72" :  "(1352,(1361,1396), c)",
"73" :  "(1352,(1396,1397), c)",
"74" :  "(1352,(1396,1408), c)",
"75" :  "(1352,1409, c)",
"76" :  "(1352,1394, c)",
"77" :  "(1352,1368, c)",
"78" :  "(1354,1354, this.lineNumber)",
"79" :  "(1362,1373, this.pos)",
"80" :  "(1362,1387, this.pos)",
"81" :  "(1362,1377, this.pos)",
"82" :  "(1362,1364, this.pos)",
"83" :  "(1365,(1367,1368), charsLoaded)",
"84" :  "(1365,(1367,1372), charsLoaded)",
"85" :  "(1366,1373, this.pos)",
"86" :  "(1366,1387, this.pos)",
"87" :  "(1366,1377, this.pos)",
"88" :  "(1373,(1374,1394), peek)",
"89" :  "(1373,(1374,1377), peek)",
"90" :  "(1373,(1374,1387), peek)",
"91" :  "(1377,1381, this.pos)",
"92" :  "(1381,(1343,1344), p)",
"93" :  "(1381,(1343,1352), p)",
"94" :  "(1381,1352, p)",
"95" :  "(1381,1344, p)",
"96" :  "(1382,(1343,1344), l)",
"97" :  "(1382,(1343,1352), l)",
"98" :  "(1382,(1363,1364), l)",
"99" :  "(1382,(1363,1372), l)",
"100" :  "(1389,(1343,1344), p)",
"101" :  "(1389,(1343,1352), p)",
"102" :  "(1389,1352, p)",
"103" :  "(1389,1344, p)",
"104" :  "(1390,(1343,1344), l)",
"105" :  "(1390,(1343,1352), l)",
"106" :  "(1390,(1363,1364), l)",
"107" :  "(1390,(1363,1372), l)",
"108" :  "(1405,(1343,1344), p)",
"109" :  "(1405,(1343,1352), p)",
"110" :  "(1405,1352, p)",
"111" :  "(1405,1344, p)",
"112" :  "(1406,(1343,1344), l)",
"113" :  "(1406,(1343,1352), l)",
"114" :  "(1406,(1363,1364), l)",
"115" :  "(1406,(1363,1372), l)"},{ "Name" : "checkLenient" ,
"Duas" : 5,
"0" :  "(1421,(1421,1422), this)",
"1" :  "(1421,(1421,1424), this)",
"2" :  "(1421,1422, this)",
"3" :  "(1421,(1421,1422), this.lenient)",
"4" :  "(1421,(1421,1424), this.lenient)"},{ "Name" : "skipToEndOfLine" ,
"Duas" : 20,
"0" :  "(1432,(1432,1432), this)",
"1" :  "(1432,(1432,1433), this)",
"2" :  "(1432,1433, this)",
"3" :  "(1432,1433, this)",
"4" :  "(1432,1435, this)",
"5" :  "(1432,1436, this)",
"6" :  "(1432,(1432,1433), this)",
"7" :  "(1432,(1432,1442), this)",
"8" :  "(1432,(1432,1432), this.limit)",
"9" :  "(1432,(1432,1433), this.limit)",
"10" :  "(1432,(1432,1432), this.pos)",
"11" :  "(1432,(1432,1433), this.pos)",
"12" :  "(1432,1433, this.pos)",
"13" :  "(1432,1433, this.buffer)",
"14" :  "(1432,1435, this.lineNumber)",
"15" :  "(1433,1436, this.pos)",
"16" :  "(1433,(1434,1435), c)",
"17" :  "(1433,(1434,1438), c)",
"18" :  "(1433,(1438,1439), c)",
"19" :  "(1433,(1438,1441), c)"},{ "Name" : "skipTo" ,
"Duas" : 44,
"0" :  "(1449,(1449,1449), this)",
"1" :  "(1449,(1449,1450), this)",
"2" :  "(1449,(1450,1451), this)",
"3" :  "(1449,(1450,1455), this)",
"4" :  "(1449,(1456,1457), this)",
"5" :  "(1449,(1456,1455), this)",
"6" :  "(1449,1449, this)",
"7" :  "(1449,1451, this)",
"8" :  "(1449,1452, this)",
"9" :  "(1449,(1449,1450), this)",
"10" :  "(1449,(1449,1462), this)",
"11" :  "(1449,(1449,1449), toFind)",
"12" :  "(1449,(1449,1450), toFind)",
"13" :  "(1449,(1455,1456), toFind)",
"14" :  "(1449,(1455,1460), toFind)",
"15" :  "(1449,(1456,1457), toFind)",
"16" :  "(1449,(1456,1455), toFind)",
"17" :  "(1449,(1449,1450), toFind)",
"18" :  "(1449,(1449,1462), toFind)",
"19" :  "(1449,(1449,1449), this.limit)",
"20" :  "(1449,(1449,1450), this.limit)",
"21" :  "(1449,(1449,1449), this.pos)",
"22" :  "(1449,(1449,1450), this.pos)",
"23" :  "(1449,(1450,1451), this.pos)",
"24" :  "(1449,(1450,1455), this.pos)",
"25" :  "(1449,(1456,1457), this.pos)",
"26" :  "(1449,(1456,1455), this.pos)",
"27" :  "(1449,1449, this.pos)",
"28" :  "(1449,1452, this.pos)",
"29" :  "(1449,(1450,1451), this.buffer)",
"30" :  "(1449,(1450,1455), this.buffer)",
"31" :  "(1449,(1456,1457), this.buffer)",
"32" :  "(1449,(1456,1455), this.buffer)",
"33" :  "(1449,1451, this.lineNumber)",
"34" :  "(1455,(1455,1456), c)",
"35" :  "(1455,(1455,1460), c)",
"36" :  "(1455,(1456,1457), c)",
"37" :  "(1455,(1456,1455), c)",
"38" :  "(1455,1455, c)",
"39" :  "(1455,(1455,1456), c)",
"40" :  "(1455,(1455,1460), c)",
"41" :  "(1455,(1456,1457), c)",
"42" :  "(1455,(1456,1455), c)",
"43" :  "(1455,1455, c)"},{ "Name" : "getPath" ,
"Duas" : 40,
"0" :  "(1475,(1477,1476), this)",
"1" :  "(1475,(1477,1480), this)",
"2" :  "(1475,(1477,1486), this)",
"3" :  "(1475,(1487,1488), this)",
"4" :  "(1475,(1487,1476), this)",
"5" :  "(1475,1488, this)",
"6" :  "(1475,1480, this)",
"7" :  "(1475,(1477,1476), this.stack)",
"8" :  "(1475,(1477,1480), this.stack)",
"9" :  "(1475,(1477,1486), this.stack)",
"10" :  "(1475,1480, this.pathIndices)",
"11" :  "(1475,(1487,1488), this.pathNames)",
"12" :  "(1475,(1487,1476), this.pathNames)",
"13" :  "(1475,1488, this.pathNames)",
"14" :  "(1475,1498, result)",
"15" :  "(1475,1486, result)",
"16" :  "(1475,1488, result)",
"17" :  "(1475,1480, result)",
"18" :  "(1476,(1476,1477), i)",
"19" :  "(1476,(1476,1498), i)",
"20" :  "(1476,(1477,1476), i)",
"21" :  "(1476,(1477,1480), i)",
"22" :  "(1476,(1477,1486), i)",
"23" :  "(1476,(1487,1488), i)",
"24" :  "(1476,(1487,1476), i)",
"25" :  "(1476,1488, i)",
"26" :  "(1476,1480, i)",
"27" :  "(1476,1476, i)",
"28" :  "(1476,(1476,1477), size)",
"29" :  "(1476,(1476,1498), size)",
"30" :  "(1476,(1476,1477), i)",
"31" :  "(1476,(1476,1498), i)",
"32" :  "(1476,(1477,1476), i)",
"33" :  "(1476,(1477,1480), i)",
"34" :  "(1476,(1477,1486), i)",
"35" :  "(1476,(1487,1488), i)",
"36" :  "(1476,(1487,1476), i)",
"37" :  "(1476,1488, i)",
"38" :  "(1476,1480, i)",
"39" :  "(1476,1476, i)"},{ "Name" : "readEscapeCharacter" ,
"Duas" : 80,
"0" :  "(1511,(1511,1511), this)",
"1" :  "(1511,(1511,1515), this)",
"2" :  "(1511,1515, this)",
"3" :  "(1511,1515, this)",
"4" :  "(1511,(1518,1518), this)",
"5" :  "(1511,(1518,1522), this)",
"6" :  "(1511,1523, this)",
"7" :  "(1511,1536, this)",
"8" :  "(1511,1524, this)",
"9" :  "(1511,1533, this)",
"10" :  "(1511,(1518,1519), this)",
"11" :  "(1511,(1518,1522), this)",
"12" :  "(1511,1519, this)",
"13" :  "(1511,1555, this)",
"14" :  "(1511,1556, this)",
"15" :  "(1511,(1511,1512), this)",
"16" :  "(1511,(1511,1515), this)",
"17" :  "(1511,1512, this)",
"18" :  "(1511,(1511,1511), this.limit)",
"19" :  "(1511,(1511,1515), this.limit)",
"20" :  "(1511,(1518,1518), this.limit)",
"21" :  "(1511,(1518,1522), this.limit)",
"22" :  "(1511,(1511,1511), this.pos)",
"23" :  "(1511,(1511,1515), this.pos)",
"24" :  "(1511,1515, this.pos)",
"25" :  "(1511,1515, this.buffer)",
"26" :  "(1511,1524, this.buffer)",
"27" :  "(1511,1533, this.buffer)",
"28" :  "(1511,1555, this.lineNumber)",
"29" :  "(1515,(1518,1518), this.pos)",
"30" :  "(1515,(1518,1522), this.pos)",
"31" :  "(1515,1523, this.pos)",
"32" :  "(1515,1536, this.pos)",
"33" :  "(1515,1533, this.pos)",
"34" :  "(1515,1556, this.pos)",
"35" :  "(1515,(1516,1563), escaped)",
"36" :  "(1515,(1516,1555), escaped)",
"37" :  "(1515,(1516,1543), escaped)",
"38" :  "(1515,(1516,1552), escaped)",
"39" :  "(1515,(1516,1546), escaped)",
"40" :  "(1515,(1516,1549), escaped)",
"41" :  "(1515,(1516,1540), escaped)",
"42" :  "(1515,(1516,1518), escaped)",
"43" :  "(1515,1563, escaped)",
"44" :  "(1522,1537, result)",
"45" :  "(1522,1525, result)",
"46" :  "(1523,(1523,1524), i)",
"47" :  "(1523,(1523,1536), i)",
"48" :  "(1523,1524, i)",
"49" :  "(1523,1523, i)",
"50" :  "(1523,(1523,1524), end)",
"51" :  "(1523,(1523,1536), end)",
"52" :  "(1524,(1526,1526), c)",
"53" :  "(1524,(1526,1528), c)",
"54" :  "(1524,(1528,1528), c)",
"55" :  "(1524,(1528,1530), c)",
"56" :  "(1524,(1530,1530), c)",
"57" :  "(1524,(1530,1533), c)",
"58" :  "(1524,(1530,1531), c)",
"59" :  "(1524,(1530,1533), c)",
"60" :  "(1524,1531, c)",
"61" :  "(1524,(1528,1529), c)",
"62" :  "(1524,(1528,1530), c)",
"63" :  "(1524,1529, c)",
"64" :  "(1524,(1526,1527), c)",
"65" :  "(1524,(1526,1528), c)",
"66" :  "(1524,1527, c)",
"67" :  "(1525,1531, result)",
"68" :  "(1525,1529, result)",
"69" :  "(1525,1527, result)",
"70" :  "(1527,1537, result)",
"71" :  "(1527,1525, result)",
"72" :  "(1529,1537, result)",
"73" :  "(1529,1525, result)",
"74" :  "(1531,1537, result)",
"75" :  "(1531,1525, result)",
"76" :  "(1523,(1523,1524), i)",
"77" :  "(1523,(1523,1536), i)",
"78" :  "(1523,1524, i)",
"79" :  "(1523,1523, i)"},{ "Name" : "consumeNonExecutePrefix" ,
"Duas" : 35,
"0" :  "(1581,(1584,1584), this)",
"1" :  "(1581,(1584,1588), this)",
"2" :  "(1581,1595, this)",
"3" :  "(1581,(1589,1590), this)",
"4" :  "(1581,(1589,1588), this)",
"5" :  "(1581,(1584,1585), this)",
"6" :  "(1581,(1584,1588), this)",
"7" :  "(1581,(1584,1584), this.limit)",
"8" :  "(1581,(1584,1588), this.limit)",
"9" :  "(1581,(1584,1584), NON_EXECUTE_PREFIX)",
"10" :  "(1581,(1584,1588), NON_EXECUTE_PREFIX)",
"11" :  "(1581,(1588,1589), NON_EXECUTE_PREFIX)",
"12" :  "(1581,(1588,1595), NON_EXECUTE_PREFIX)",
"13" :  "(1581,1595, NON_EXECUTE_PREFIX)",
"14" :  "(1581,(1589,1590), NON_EXECUTE_PREFIX)",
"15" :  "(1581,(1589,1588), NON_EXECUTE_PREFIX)",
"16" :  "(1581,(1584,1585), NON_EXECUTE_PREFIX)",
"17" :  "(1581,(1584,1588), NON_EXECUTE_PREFIX)",
"18" :  "(1581,(1589,1590), this.buffer)",
"19" :  "(1581,(1589,1588), this.buffer)",
"20" :  "(1582,(1584,1584), this.pos)",
"21" :  "(1582,(1584,1588), this.pos)",
"22" :  "(1582,1595, this.pos)",
"23" :  "(1582,(1589,1590), this.pos)",
"24" :  "(1582,(1589,1588), this.pos)",
"25" :  "(1588,(1588,1589), i)",
"26" :  "(1588,(1588,1595), i)",
"27" :  "(1588,(1589,1590), i)",
"28" :  "(1588,(1589,1588), i)",
"29" :  "(1588,1588, i)",
"30" :  "(1588,(1588,1589), i)",
"31" :  "(1588,(1588,1595), i)",
"32" :  "(1588,(1589,1590), i)",
"33" :  "(1588,(1589,1588), i)",
"34" :  "(1588,1588, i)"}]
}