{
"Class" : "com.fasterxml.jackson.databind.ser.std.BeanSerializerBase", 
"Methods" : [{ "Name" : "<init>" ,
"Duas" : 20,
"0" :  "(108,118, this)",
"1" :  "(108,119, this)",
"2" :  "(108,120, this)",
"3" :  "(108,121, this)",
"4" :  "(108,123, this)",
"5" :  "(108,112, this)",
"6" :  "(108,113, this)",
"7" :  "(108,114, this)",
"8" :  "(108,115, this)",
"9" :  "(108,116, this)",
"10" :  "(108,(111,112), builder)",
"11" :  "(108,(111,118), builder)",
"12" :  "(108,118, builder)",
"13" :  "(108,119, builder)",
"14" :  "(108,120, builder)",
"15" :  "(108,121, builder)",
"16" :  "(108,122, builder)",
"17" :  "(122,(123,123), format)",
"18" :  "(122,(123,123), format)",
"19" :  "(122,123, format)"},{ "Name" : "<init>" ,
"Duas" : 47,
"0" :  "(166,188, this)",
"1" :  "(166,189, this)",
"2" :  "(166,191, this)",
"3" :  "(166,192, this)",
"4" :  "(166,193, this)",
"5" :  "(166,194, this)",
"6" :  "(166,195, this)",
"7" :  "(166,191, src)",
"8" :  "(166,192, src)",
"9" :  "(166,193, src)",
"10" :  "(166,194, src)",
"11" :  "(166,195, src)",
"12" :  "(166,191, src._typeId)",
"13" :  "(166,192, src._anyGetterWriter)",
"14" :  "(166,193, src._objectIdWriter)",
"15" :  "(166,194, src._propertyFilterId)",
"16" :  "(166,195, src._serializationShape)",
"17" :  "(169,(180,181), ignoredSet)",
"18" :  "(169,(180,183), ignoredSet)",
"19" :  "(170,178, propsIn)",
"20" :  "(171,(175,175), fpropsIn)",
"21" :  "(171,(175,175), fpropsIn)",
"22" :  "(171,(184,185), fpropsIn)",
"23" :  "(171,(184,177), fpropsIn)",
"24" :  "(171,185, fpropsIn)",
"25" :  "(172,175, len)",
"26" :  "(172,(177,178), len)",
"27" :  "(172,(177,188), len)",
"28" :  "(174,188, propsOut)",
"29" :  "(174,183, propsOut)",
"30" :  "(175,(189,189), fpropsOut)",
"31" :  "(175,(189,189), fpropsOut)",
"32" :  "(175,189, fpropsOut)",
"33" :  "(175,185, fpropsOut)",
"34" :  "(177,(177,178), i)",
"35" :  "(177,(177,188), i)",
"36" :  "(177,178, i)",
"37" :  "(177,177, i)",
"38" :  "(177,185, i)",
"39" :  "(178,(180,181), bpw)",
"40" :  "(178,(180,183), bpw)",
"41" :  "(178,183, bpw)",
"42" :  "(177,(177,178), i)",
"43" :  "(177,(177,188), i)",
"44" :  "(177,178, i)",
"45" :  "(177,177, i)",
"46" :  "(177,185, i)"},{ "Name" : "rename" ,
"Duas" : 31,
"0" :  "(251,(251,251), props)",
"1" :  "(251,(251,252), props)",
"2" :  "(251,252, props)",
"3" :  "(251,(251,251), props)",
"4" :  "(251,(251,252), props)",
"5" :  "(251,254, props)",
"6" :  "(251,257, props)",
"7" :  "(251,(251,251), transformer)",
"8" :  "(251,(251,252), transformer)",
"9" :  "(251,(251,252), transformer)",
"10" :  "(251,(251,254), transformer)",
"11" :  "(251,259, transformer)",
"12" :  "(251,(251,252), NOP)",
"13" :  "(251,(251,254), NOP)",
"14" :  "(254,(256,257), len)",
"15" :  "(254,(256,262), len)",
"16" :  "(255,262, result)",
"17" :  "(255,259, result)",
"18" :  "(256,(256,257), i)",
"19" :  "(256,(256,262), i)",
"20" :  "(256,257, i)",
"21" :  "(256,256, i)",
"22" :  "(256,259, i)",
"23" :  "(257,(258,259), bpw)",
"24" :  "(257,(258,256), bpw)",
"25" :  "(257,259, bpw)",
"26" :  "(256,(256,257), i)",
"27" :  "(256,(256,262), i)",
"28" :  "(256,257, i)",
"29" :  "(256,256, i)",
"30" :  "(256,259, i)"},{ "Name" : "resolve" ,
"Duas" : 106,
"0" :  "(279,(279,279), this)",
"1" :  "(279,(279,279), this)",
"2" :  "(279,279, this)",
"3" :  "(279,280, this)",
"4" :  "(279,(348,350), this)",
"5" :  "(279,(348,352), this)",
"6" :  "(279,350, this)",
"7" :  "(279,281, this)",
"8" :  "(279,301, this)",
"9" :  "(279,340, this)",
"10" :  "(279,289, this)",
"11" :  "(279,350, provider)",
"12" :  "(279,301, provider)",
"13" :  "(279,320, provider)",
"14" :  "(279,284, provider)",
"15" :  "(279,(279,279), this._filteredProps)",
"16" :  "(279,(279,279), this._filteredProps)",
"17" :  "(279,279, this._filteredProps)",
"18" :  "(279,340, this._filteredProps)",
"19" :  "(279,289, this._filteredProps)",
"20" :  "(279,280, this._props)",
"21" :  "(279,281, this._props)",
"22" :  "(279,(348,350), this._anyGetterWriter)",
"23" :  "(279,(348,352), this._anyGetterWriter)",
"24" :  "(279,350, this._anyGetterWriter)",
"25" :  "(279,(339,340), filteredCount)",
"26" :  "(279,(339,280), filteredCount)",
"27" :  "(279,(288,289), filteredCount)",
"28" :  "(279,(288,297), filteredCount)",
"29" :  "(280,(280,281), i)",
"30" :  "(280,(280,348), i)",
"31" :  "(280,281, i)",
"32" :  "(280,(339,340), i)",
"33" :  "(280,(339,280), i)",
"34" :  "(280,280, i)",
"35" :  "(280,340, i)",
"36" :  "(280,(288,289), i)",
"37" :  "(280,(288,297), i)",
"38" :  "(280,289, i)",
"39" :  "(280,(280,281), len)",
"40" :  "(280,(280,348), len)",
"41" :  "(281,(283,283), prop)",
"42" :  "(281,(283,297), prop)",
"43" :  "(281,(297,298), prop)",
"44" :  "(281,(297,301), prop)",
"45" :  "(281,301, prop)",
"46" :  "(281,337, prop)",
"47" :  "(281,304, prop)",
"48" :  "(281,320, prop)",
"49" :  "(281,312, prop)",
"50" :  "(281,315, prop)",
"51" :  "(281,(283,284), prop)",
"52" :  "(281,(283,297), prop)",
"53" :  "(281,284, prop)",
"54" :  "(281,286, prop)",
"55" :  "(284,(285,286), nullSer)",
"56" :  "(284,(285,297), nullSer)",
"57" :  "(284,286, nullSer)",
"58" :  "(284,291, nullSer)",
"59" :  "(289,(290,291), w2)",
"60" :  "(289,(290,297), w2)",
"61" :  "(289,291, w2)",
"62" :  "(301,(302,304), ser)",
"63" :  "(301,(302,337), ser)",
"64" :  "(301,337, ser)",
"65" :  "(301,342, ser)",
"66" :  "(304,(308,312), type)",
"67" :  "(304,(308,320), type)",
"68" :  "(304,320, type)",
"69" :  "(304,(324,325), type)",
"70" :  "(304,(324,337), type)",
"71" :  "(304,325, type)",
"72" :  "(312,(313,314), type)",
"73" :  "(312,(313,320), type)",
"74" :  "(312,320, type)",
"75" :  "(312,(324,325), type)",
"76" :  "(312,(324,337), type)",
"77" :  "(312,325, type)",
"78" :  "(312,(314,314), type)",
"79" :  "(312,(314,315), type)",
"80" :  "(312,315, type)",
"81" :  "(312,(314,315), type)",
"82" :  "(312,(314,280), type)",
"83" :  "(320,337, ser)",
"84" :  "(320,342, ser)",
"85" :  "(320,(328,331), ser)",
"86" :  "(320,(328,337), ser)",
"87" :  "(320,331, ser)",
"88" :  "(325,(326,328), typeSer)",
"89" :  "(325,(326,337), typeSer)",
"90" :  "(325,331, typeSer)",
"91" :  "(332,337, ser)",
"92" :  "(332,342, ser)",
"93" :  "(340,(341,342), w2)",
"94" :  "(340,(341,280), w2)",
"95" :  "(340,342, w2)",
"96" :  "(280,(280,281), i)",
"97" :  "(280,(280,348), i)",
"98" :  "(280,281, i)",
"99" :  "(280,(339,340), i)",
"100" :  "(280,(339,280), i)",
"101" :  "(280,280, i)",
"102" :  "(280,340, i)",
"103" :  "(280,(288,289), i)",
"104" :  "(280,(288,297), i)",
"105" :  "(280,289, i)"},{ "Name" : "findConvertingSerializer" ,
"Duas" : 20,
"0" :  "(365,371, provider)",
"1" :  "(365,372, provider)",
"2" :  "(365,374, provider)",
"3" :  "(365,367, prop)",
"4" :  "(365,371, prop)",
"5" :  "(365,374, prop)",
"6" :  "(365,(366,367), intr)",
"7" :  "(365,(366,380), intr)",
"8" :  "(365,369, intr)",
"9" :  "(367,(368,369), m)",
"10" :  "(367,(368,380), m)",
"11" :  "(367,369, m)",
"12" :  "(369,(370,371), convDef)",
"13" :  "(369,(370,380), convDef)",
"14" :  "(369,371, convDef)",
"15" :  "(371,376, conv)",
"16" :  "(372,(374,374), delegateType)",
"17" :  "(372,(374,374), delegateType)",
"18" :  "(372,374, delegateType)",
"19" :  "(372,376, delegateType)"},{ "Name" : "createContextual" ,
"Duas" : 206,
"0" :  "(389,421, this)",
"1" :  "(389,494, this)",
"2" :  "(389,510, this)",
"3" :  "(389,(498,499), this)",
"4" :  "(389,(498,503), this)",
"5" :  "(389,(488,488), this)",
"6" :  "(389,(488,489), this)",
"7" :  "(389,(488,489), this)",
"8" :  "(389,(488,494), this)",
"9" :  "(389,451, this)",
"10" :  "(389,456, this)",
"11" :  "(389,463, this)",
"12" :  "(389,464, this)",
"13" :  "(389,(465,466), this)",
"14" :  "(389,(465,474), this)",
"15" :  "(389,466, this)",
"16" :  "(389,467, this)",
"17" :  "(389,468, this)",
"18" :  "(389,453, this)",
"19" :  "(389,434, this)",
"20" :  "(389,(403,404), this)",
"21" :  "(389,(403,421), this)",
"22" :  "(389,(404,405), this)",
"23" :  "(389,(404,421), this)",
"24" :  "(389,411, this)",
"25" :  "(389,412, this)",
"26" :  "(389,392, provider)",
"27" :  "(389,496, provider)",
"28" :  "(389,444, provider)",
"29" :  "(389,445, provider)",
"30" :  "(389,478, provider)",
"31" :  "(389,412, provider)",
"32" :  "(389,414, provider)",
"33" :  "(389,(390,390), property)",
"34" :  "(389,(390,390), property)",
"35" :  "(389,390, property)",
"36" :  "(389,496, property)",
"37" :  "(389,414, property)",
"38" :  "(389,510, this._serializationShape)",
"39" :  "(389,(403,404), this._serializationShape)",
"40" :  "(389,(403,421), this._serializationShape)",
"41" :  "(389,453, this._handledType)",
"42" :  "(389,(404,405), this._handledType)",
"43" :  "(389,(404,421), this._handledType)",
"44" :  "(389,411, this._handledType)",
"45" :  "(389,412, this._handledType)",
"46" :  "(389,(405,421), $SwitchMap$com$fasterxml$jackson$annotation$JsonFormat$Shape)",
"47" :  "(389,(405,411), $SwitchMap$com$fasterxml$jackson$annotation$JsonFormat$Shape)",
"48" :  "(389,421, this._objectIdWriter)",
"49" :  "(389,(498,499), this._objectIdWriter)",
"50" :  "(389,(498,503), this._objectIdWriter)",
"51" :  "(389,434, this._objectIdWriter)",
"52" :  "(389,432, NAME_FOR_OBJECT_REF)",
"53" :  "(389,451, this._props)",
"54" :  "(389,456, this._props)",
"55" :  "(389,463, this._props)",
"56" :  "(389,464, this._props)",
"57" :  "(389,(465,466), this._filteredProps)",
"58" :  "(389,(465,474), this._filteredProps)",
"59" :  "(389,466, this._filteredProps)",
"60" :  "(389,467, this._filteredProps)",
"61" :  "(389,468, this._filteredProps)",
"62" :  "(389,(488,488), this._propertyFilterId)",
"63" :  "(389,(488,489), this._propertyFilterId)",
"64" :  "(389,(488,489), this._propertyFilterId)",
"65" :  "(389,(488,494), this._propertyFilterId)",
"66" :  "(389,(512,513), ARRAY)",
"67" :  "(389,(512,515), ARRAY)",
"68" :  "(389,427, intr)",
"69" :  "(389,428, intr)",
"70" :  "(389,441, intr)",
"71" :  "(389,485, intr)",
"72" :  "(389,432, intr)",
"73" :  "(389,398, intr)",
"74" :  "(389,(390,390), intr)",
"75" :  "(389,(390,390), intr)",
"76" :  "(390,(397,398), accessor)",
"77" :  "(390,(397,421), accessor)",
"78" :  "(390,(426,427), accessor)",
"79" :  "(390,(426,494), accessor)",
"80" :  "(390,427, accessor)",
"81" :  "(390,428, accessor)",
"82" :  "(390,441, accessor)",
"83" :  "(390,478, accessor)",
"84" :  "(390,485, accessor)",
"85" :  "(390,432, accessor)",
"86" :  "(390,398, accessor)",
"87" :  "(392,411, config)",
"88" :  "(396,(509,510), shape)",
"89" :  "(396,(509,512), shape)",
"90" :  "(396,(512,513), shape)",
"91" :  "(396,(512,515), shape)",
"92" :  "(398,(400,401), format)",
"93" :  "(398,(400,421), format)",
"94" :  "(398,401, format)",
"95" :  "(398,412, format)",
"96" :  "(401,(403,404), shape)",
"97" :  "(401,(403,421), shape)",
"98" :  "(401,(509,510), shape)",
"99" :  "(401,(509,512), shape)",
"100" :  "(401,(512,513), shape)",
"101" :  "(401,(512,515), shape)",
"102" :  "(401,(405,421), shape)",
"103" :  "(401,(405,411), shape)",
"104" :  "(421,(495,496), oiw)",
"105" :  "(421,(495,503), oiw)",
"106" :  "(421,496, oiw)",
"107" :  "(421,497, oiw)",
"108" :  "(421,(431,432), oiw)",
"109" :  "(421,(431,485), oiw)",
"110" :  "(421,496, oiw.idType)",
"111" :  "(422,(503,503), ignorals)",
"112" :  "(422,(503,506), ignorals)",
"113" :  "(422,(503,504), ignorals)",
"114" :  "(422,(503,506), ignorals)",
"115" :  "(422,504, ignorals)",
"116" :  "(423,(506,507), newFilterId)",
"117" :  "(423,(506,509), newFilterId)",
"118" :  "(423,507, newFilterId)",
"119" :  "(427,(503,503), ignorals)",
"120" :  "(427,(503,506), ignorals)",
"121" :  "(427,(503,504), ignorals)",
"122" :  "(427,(503,506), ignorals)",
"123" :  "(427,504, ignorals)",
"124" :  "(428,(429,431), objectIdInfo)",
"125" :  "(428,(429,441), objectIdInfo)",
"126" :  "(428,441, objectIdInfo)",
"127" :  "(434,(495,496), oiw)",
"128" :  "(434,(495,503), oiw)",
"129" :  "(434,496, oiw)",
"130" :  "(434,497, oiw)",
"131" :  "(434,496, oiw.idType)",
"132" :  "(441,478, objectIdInfo)",
"133" :  "(441,479, objectIdInfo)",
"134" :  "(441,448, objectIdInfo)",
"135" :  "(441,475, objectIdInfo)",
"136" :  "(441,476, objectIdInfo)",
"137" :  "(443,(447,448), implClass)",
"138" :  "(443,(447,478), implClass)",
"139" :  "(445,479, idType)",
"140" :  "(448,(457,458), propName)",
"141" :  "(448,(457,451), propName)",
"142" :  "(448,453, propName)",
"143" :  "(451,(452,453), i)",
"144" :  "(451,(452,456), i)",
"145" :  "(451,456, i)",
"146" :  "(451,451, i)",
"147" :  "(451,(462,463), i)",
"148" :  "(451,(462,474), i)",
"149" :  "(451,463, i)",
"150" :  "(451,466, i)",
"151" :  "(451,467, i)",
"152" :  "(451,(452,453), len)",
"153" :  "(451,(452,456), len)",
"154" :  "(456,(457,458), prop)",
"155" :  "(456,(457,451), prop)",
"156" :  "(456,458, prop)",
"157" :  "(458,474, idProp)",
"158" :  "(458,475, idProp)",
"159" :  "(458,464, idProp)",
"160" :  "(451,(452,453), i)",
"161" :  "(451,(452,456), i)",
"162" :  "(451,456, i)",
"163" :  "(451,451, i)",
"164" :  "(451,(462,463), i)",
"165" :  "(451,(462,474), i)",
"166" :  "(451,463, i)",
"167" :  "(451,466, i)",
"168" :  "(451,467, i)",
"169" :  "(476,(495,496), oiw)",
"170" :  "(476,(495,503), oiw)",
"171" :  "(476,496, oiw)",
"172" :  "(476,497, oiw)",
"173" :  "(476,496, oiw.idType)",
"174" :  "(479,(495,496), oiw)",
"175" :  "(479,(495,503), oiw)",
"176" :  "(479,496, oiw)",
"177" :  "(479,497, oiw)",
"178" :  "(479,496, oiw.idType)",
"179" :  "(485,(486,488), filterId)",
"180" :  "(485,(486,494), filterId)",
"181" :  "(485,489, filterId)",
"182" :  "(485,(488,489), filterId)",
"183" :  "(485,(488,494), filterId)",
"184" :  "(489,(506,507), newFilterId)",
"185" :  "(489,(506,509), newFilterId)",
"186" :  "(489,507, newFilterId)",
"187" :  "(494,515, contextual)",
"188" :  "(494,513, contextual)",
"189" :  "(494,507, contextual)",
"190" :  "(494,504, contextual)",
"191" :  "(494,499, contextual)",
"192" :  "(497,(498,499), oiw)",
"193" :  "(497,(498,503), oiw)",
"194" :  "(497,499, oiw)",
"195" :  "(499,515, contextual)",
"196" :  "(499,513, contextual)",
"197" :  "(499,507, contextual)",
"198" :  "(499,504, contextual)",
"199" :  "(504,515, contextual)",
"200" :  "(504,513, contextual)",
"201" :  "(504,507, contextual)",
"202" :  "(507,515, contextual)",
"203" :  "(507,513, contextual)",
"204" :  "(510,(512,513), shape)",
"205" :  "(510,(512,515), shape)"},{ "Name" : "usesObjectId" ,
"Duas" : 4,
"0" :  "(537,(537,537), this)",
"1" :  "(537,(537,537), this)",
"2" :  "(537,(537,537), this._objectIdWriter)",
"3" :  "(537,(537,537), this._objectIdWriter)"},{ "Name" : "serializeWithType" ,
"Duas" : 49,
"0" :  "(551,(551,552), this)",
"1" :  "(551,(551,557), this)",
"2" :  "(551,(557,557), this)",
"3" :  "(551,(557,557), this)",
"4" :  "(551,557, this)",
"5" :  "(551,(564,565), this)",
"6" :  "(551,(564,567), this)",
"7" :  "(551,567, this)",
"8" :  "(551,565, this)",
"9" :  "(551,553, this)",
"10" :  "(551,557, bean)",
"11" :  "(551,561, bean)",
"12" :  "(551,563, bean)",
"13" :  "(551,567, bean)",
"14" :  "(551,572, bean)",
"15" :  "(551,570, bean)",
"16" :  "(551,565, bean)",
"17" :  "(551,559, bean)",
"18" :  "(551,552, bean)",
"19" :  "(551,553, bean)",
"20" :  "(551,561, gen)",
"21" :  "(551,563, gen)",
"22" :  "(551,567, gen)",
"23" :  "(551,572, gen)",
"24" :  "(551,570, gen)",
"25" :  "(551,565, gen)",
"26" :  "(551,559, gen)",
"27" :  "(551,552, gen)",
"28" :  "(551,553, gen)",
"29" :  "(551,567, provider)",
"30" :  "(551,565, provider)",
"31" :  "(551,553, provider)",
"32" :  "(551,561, typeSer)",
"33" :  "(551,572, typeSer)",
"34" :  "(551,570, typeSer)",
"35" :  "(551,559, typeSer)",
"36" :  "(551,553, typeSer)",
"37" :  "(551,(551,552), this._objectIdWriter)",
"38" :  "(551,(551,557), this._objectIdWriter)",
"39" :  "(551,(557,557), this._typeId)",
"40" :  "(551,(557,557), this._typeId)",
"41" :  "(551,(564,565), this._propertyFilterId)",
"42" :  "(551,(564,567), this._propertyFilterId)",
"43" :  "(557,(558,559), typeStr)",
"44" :  "(557,(558,561), typeStr)",
"45" :  "(557,561, typeStr)",
"46" :  "(557,(569,570), typeStr)",
"47" :  "(557,(569,572), typeStr)",
"48" :  "(557,572, typeStr)"},{ "Name" : "_serializeWithObjectId" ,
"Duas" : 41,
"0" :  "(579,(595,596), this)",
"1" :  "(579,(595,598), this)",
"2" :  "(579,598, this)",
"3" :  "(579,596, this)",
"4" :  "(579,586, bean)",
"5" :  "(579,598, bean)",
"6" :  "(579,596, bean)",
"7" :  "(579,(582,583), gen)",
"8" :  "(579,(582,586), gen)",
"9" :  "(579,594, gen)",
"10" :  "(579,598, gen)",
"11" :  "(579,601, gen)",
"12" :  "(579,596, gen)",
"13" :  "(579,592, gen)",
"14" :  "(579,588, gen)",
"15" :  "(579,(582,583), provider)",
"16" :  "(579,(582,586), provider)",
"17" :  "(579,594, provider)",
"18" :  "(579,598, provider)",
"19" :  "(579,596, provider)",
"20" :  "(579,588, provider)",
"21" :  "(579,(591,592), startEndObject)",
"22" :  "(579,(591,594), startEndObject)",
"23" :  "(579,(600,601), startEndObject)",
"24" :  "(579,(600,603), startEndObject)",
"25" :  "(579,(595,596), this._propertyFilterId)",
"26" :  "(579,(595,598), this._propertyFilterId)",
"27" :  "(579,(582,583), w)",
"28" :  "(579,(582,586), w)",
"29" :  "(579,(587,588), w)",
"30" :  "(579,(587,591), w)",
"31" :  "(579,594, w)",
"32" :  "(579,588, w)",
"33" :  "(579,(587,588), w.alwaysAsId)",
"34" :  "(579,(587,591), w.alwaysAsId)",
"35" :  "(579,588, w.serializer)",
"36" :  "(580,(582,583), objectId)",
"37" :  "(580,(582,586), objectId)",
"38" :  "(580,586, objectId)",
"39" :  "(580,594, objectId)",
"40" :  "(586,588, id)"},{ "Name" : "_serializeWithObjectId" ,
"Duas" : 25,
"0" :  "(608,621, this)",
"1" :  "(608,615, bean)",
"2" :  "(608,621, bean)",
"3" :  "(608,(611,612), gen)",
"4" :  "(608,(611,615), gen)",
"5" :  "(608,621, gen)",
"6" :  "(608,617, gen)",
"7" :  "(608,(611,612), provider)",
"8" :  "(608,(611,615), provider)",
"9" :  "(608,621, provider)",
"10" :  "(608,617, provider)",
"11" :  "(608,621, typeSer)",
"12" :  "(608,(611,612), w)",
"13" :  "(608,(611,615), w)",
"14" :  "(608,(616,617), w)",
"15" :  "(608,(616,621), w)",
"16" :  "(608,617, w)",
"17" :  "(608,(616,617), w.alwaysAsId)",
"18" :  "(608,(616,621), w.alwaysAsId)",
"19" :  "(608,617, w.serializer)",
"20" :  "(609,(611,612), objectId)",
"21" :  "(609,(611,615), objectId)",
"22" :  "(609,615, objectId)",
"23" :  "(609,621, objectId)",
"24" :  "(615,617, id)"},{ "Name" : "_serializeObjectId" ,
"Duas" : 40,
"0" :  "(627,(628,628), this)",
"1" :  "(627,(628,628), this)",
"2" :  "(627,628, this)",
"3" :  "(627,(635,636), this)",
"4" :  "(627,(635,638), this)",
"5" :  "(627,638, this)",
"6" :  "(627,636, this)",
"7" :  "(627,628, bean)",
"8" :  "(627,632, bean)",
"9" :  "(627,638, bean)",
"10" :  "(627,643, bean)",
"11" :  "(627,641, bean)",
"12" :  "(627,636, bean)",
"13" :  "(627,630, bean)",
"14" :  "(627,632, gen)",
"15" :  "(627,634, gen)",
"16" :  "(627,638, gen)",
"17" :  "(627,643, gen)",
"18" :  "(627,641, gen)",
"19" :  "(627,636, gen)",
"20" :  "(627,630, gen)",
"21" :  "(627,634, provider)",
"22" :  "(627,638, provider)",
"23" :  "(627,636, provider)",
"24" :  "(627,632, typeSer)",
"25" :  "(627,643, typeSer)",
"26" :  "(627,641, typeSer)",
"27" :  "(627,630, typeSer)",
"28" :  "(627,634, objectId)",
"29" :  "(627,(628,628), this._typeId)",
"30" :  "(627,(628,628), this._typeId)",
"31" :  "(627,(635,636), this._propertyFilterId)",
"32" :  "(627,(635,638), this._propertyFilterId)",
"33" :  "(627,634, w)",
"34" :  "(628,(629,630), typeStr)",
"35" :  "(628,(629,632), typeStr)",
"36" :  "(628,632, typeStr)",
"37" :  "(628,(640,641), typeStr)",
"38" :  "(628,(640,643), typeStr)",
"39" :  "(628,643, typeStr)"},{ "Name" : "_customTypeId" ,
"Duas" : 5,
"0" :  "(649,(650,651), typeId)",
"1" :  "(649,(650,653), typeId)",
"2" :  "(649,(653,653), typeId)",
"3" :  "(649,(653,653), typeId)",
"4" :  "(649,653, typeId)"},{ "Name" : "serializeFields" ,
"Duas" : 39,
"0" :  "(666,(666,666), this)",
"1" :  "(666,(666,669), this)",
"2" :  "(666,669, this)",
"3" :  "(666,(679,680), this)",
"4" :  "(666,(679,697), this)",
"5" :  "(666,680, this)",
"6" :  "(666,667, this)",
"7" :  "(666,680, bean)",
"8" :  "(666,676, bean)",
"9" :  "(666,680, gen)",
"10" :  "(666,676, gen)",
"11" :  "(666,680, provider)",
"12" :  "(666,676, provider)",
"13" :  "(666,(666,667), provider)",
"14" :  "(666,(666,669), provider)",
"15" :  "(666,(666,666), this._filteredProps)",
"16" :  "(666,(666,669), this._filteredProps)",
"17" :  "(666,667, this._filteredProps)",
"18" :  "(666,669, this._props)",
"19" :  "(666,(679,680), this._anyGetterWriter)",
"20" :  "(666,(679,697), this._anyGetterWriter)",
"21" :  "(666,680, this._anyGetterWriter)",
"22" :  "(667,673, props)",
"23" :  "(667,674, props)",
"24" :  "(669,673, props)",
"25" :  "(669,674, props)",
"26" :  "(671,(673,674), i)",
"27" :  "(671,(673,679), i)",
"28" :  "(671,674, i)",
"29" :  "(671,673, i)",
"30" :  "(673,(673,674), len)",
"31" :  "(673,(673,679), len)",
"32" :  "(674,(675,676), prop)",
"33" :  "(674,(675,673), prop)",
"34" :  "(674,676, prop)",
"35" :  "(673,(673,674), i)",
"36" :  "(673,(673,679), i)",
"37" :  "(673,674, i)",
"38" :  "(673,673, i)"},{ "Name" : "serializeFieldsFiltered" ,
"Duas" : 51,
"0" :  "(713,(713,713), this)",
"1" :  "(713,(713,716), this)",
"2" :  "(713,716, this)",
"3" :  "(713,718, this)",
"4" :  "(713,(732,733), this)",
"5" :  "(713,(732,745), this)",
"6" :  "(713,733, this)",
"7" :  "(713,721, this)",
"8" :  "(713,714, this)",
"9" :  "(713,718, bean)",
"10" :  "(713,733, bean)",
"11" :  "(713,729, bean)",
"12" :  "(713,721, bean)",
"13" :  "(713,733, gen)",
"14" :  "(713,729, gen)",
"15" :  "(713,721, gen)",
"16" :  "(713,718, provider)",
"17" :  "(713,733, provider)",
"18" :  "(713,729, provider)",
"19" :  "(713,721, provider)",
"20" :  "(713,(713,714), provider)",
"21" :  "(713,(713,716), provider)",
"22" :  "(713,(713,713), this._filteredProps)",
"23" :  "(713,(713,716), this._filteredProps)",
"24" :  "(713,714, this._filteredProps)",
"25" :  "(713,716, this._props)",
"26" :  "(713,718, this._propertyFilterId)",
"27" :  "(713,(732,733), this._anyGetterWriter)",
"28" :  "(713,(732,745), this._anyGetterWriter)",
"29" :  "(713,733, this._anyGetterWriter)",
"30" :  "(714,726, props)",
"31" :  "(714,727, props)",
"32" :  "(716,726, props)",
"33" :  "(716,727, props)",
"34" :  "(718,(720,721), filter)",
"35" :  "(718,(720,724), filter)",
"36" :  "(718,733, filter)",
"37" :  "(718,729, filter)",
"38" :  "(724,(726,727), i)",
"39" :  "(724,(726,732), i)",
"40" :  "(724,727, i)",
"41" :  "(724,726, i)",
"42" :  "(726,(726,727), len)",
"43" :  "(726,(726,732), len)",
"44" :  "(727,(728,729), prop)",
"45" :  "(727,(728,726), prop)",
"46" :  "(727,729, prop)",
"47" :  "(726,(726,727), i)",
"48" :  "(726,(726,732), i)",
"49" :  "(726,727, i)",
"50" :  "(726,726, i)"},{ "Name" : "getSchema" ,
"Duas" : 46,
"0" :  "(753,(768,769), this)",
"1" :  "(753,(768,771), this)",
"2" :  "(753,(774,775), this)",
"3" :  "(753,(774,783), this)",
"4" :  "(753,775, this)",
"5" :  "(753,769, this)",
"6" :  "(753,779, provider)",
"7" :  "(753,777, provider)",
"8" :  "(753,769, provider)",
"9" :  "(753,(768,769), this._propertyFilterId)",
"10" :  "(753,(768,771), this._propertyFilterId)",
"11" :  "(753,769, this._propertyFilterId)",
"12" :  "(753,(774,775), this._props)",
"13" :  "(753,(774,783), this._props)",
"14" :  "(753,775, this._props)",
"15" :  "(753,766, o)",
"16" :  "(753,783, o)",
"17" :  "(753,784, o)",
"18" :  "(753,760, o)",
"19" :  "(756,(757,758), ann)",
"20" :  "(756,(757,766), ann)",
"21" :  "(756,758, ann)",
"22" :  "(758,(759,759), id)",
"23" :  "(758,(759,766), id)",
"24" :  "(758,(759,760), id)",
"25" :  "(758,(759,766), id)",
"26" :  "(758,760, id)",
"27" :  "(766,783, propertiesNode)",
"28" :  "(766,779, propertiesNode)",
"29" :  "(766,777, propertiesNode)",
"30" :  "(769,(776,777), filter)",
"31" :  "(769,(776,779), filter)",
"32" :  "(769,779, filter)",
"33" :  "(771,(776,777), filter)",
"34" :  "(771,(776,779), filter)",
"35" :  "(771,779, filter)",
"36" :  "(774,(774,775), i)",
"37" :  "(774,(774,783), i)",
"38" :  "(774,775, i)",
"39" :  "(774,774, i)",
"40" :  "(775,779, prop)",
"41" :  "(775,777, prop)",
"42" :  "(774,(774,775), i)",
"43" :  "(774,(774,783), i)",
"44" :  "(774,775, i)",
"45" :  "(774,774, i)"},{ "Name" : "acceptJsonFormatVisitor" ,
"Duas" : 63,
"0" :  "(792,(800,801), this)",
"1" :  "(792,(800,807), this)",
"2" :  "(792,(807,807), this)",
"3" :  "(792,(807,807), this)",
"4" :  "(792,813, this)",
"5" :  "(792,811, this)",
"6" :  "(792,801, this)",
"7" :  "(792,803, this)",
"8" :  "(792,804, this)",
"9" :  "(792,(792,793), visitor)",
"10" :  "(792,(792,795), visitor)",
"11" :  "(792,795, visitor)",
"12" :  "(792,799, visitor)",
"13" :  "(792,801, visitor)",
"14" :  "(792,795, typeHint)",
"15" :  "(792,(800,801), this._propertyFilterId)",
"16" :  "(792,(800,807), this._propertyFilterId)",
"17" :  "(792,801, this._propertyFilterId)",
"18" :  "(792,813, this._props)",
"19" :  "(792,803, this._props)",
"20" :  "(792,804, this._props)",
"21" :  "(792,(807,807), this._filteredProps)",
"22" :  "(792,(807,807), this._filteredProps)",
"23" :  "(792,811, this._filteredProps)",
"24" :  "(795,(796,797), objectVisitor)",
"25" :  "(795,(796,799), objectVisitor)",
"26" :  "(795,819, objectVisitor)",
"27" :  "(795,804, objectVisitor)",
"28" :  "(799,807, provider)",
"29" :  "(799,819, provider)",
"30" :  "(799,(807,807), provider)",
"31" :  "(799,(807,807), provider)",
"32" :  "(799,804, provider)",
"33" :  "(801,804, filter)",
"34" :  "(803,(803,804), i)",
"35" :  "(803,(803,806), i)",
"36" :  "(803,804, i)",
"37" :  "(803,803, i)",
"38" :  "(803,(803,804), end)",
"39" :  "(803,(803,806), end)",
"40" :  "(803,(803,804), i)",
"41" :  "(803,(803,806), i)",
"42" :  "(803,804, i)",
"43" :  "(803,803, i)",
"44" :  "(807,(810,811), view)",
"45" :  "(807,(810,813), view)",
"46" :  "(811,816, props)",
"47" :  "(811,817, props)",
"48" :  "(813,816, props)",
"49" :  "(813,817, props)",
"50" :  "(816,(816,817), i)",
"51" :  "(816,(816,823), i)",
"52" :  "(816,817, i)",
"53" :  "(816,816, i)",
"54" :  "(816,(816,817), end)",
"55" :  "(816,(816,823), end)",
"56" :  "(817,(818,819), prop)",
"57" :  "(817,(818,816), prop)",
"58" :  "(817,819, prop)",
"59" :  "(816,(816,817), i)",
"60" :  "(816,(816,823), i)",
"61" :  "(816,817, i)",
"62" :  "(816,816, i)"}]
}