{
"Class" : "org.apache.commons.cli2.builder.PatternBuilder", 
"Methods" : [{ "Name" : "create" ,
"Duas" : 20,
"0" :  "(76,(76,77), this)",
"1" :  "(76,(76,80), this)",
"2" :  "(76,80, this)",
"3" :  "(76,81, this)",
"4" :  "(76,84, this)",
"5" :  "(76,87, this)",
"6" :  "(76,82, this)",
"7" :  "(76,77, this)",
"8" :  "(76,(76,77), this.options)",
"9" :  "(76,(76,80), this.options)",
"10" :  "(76,81, this.options)",
"11" :  "(76,77, this.options)",
"12" :  "(76,80, this.gbuilder)",
"13" :  "(76,84, this.gbuilder)",
"14" :  "(76,82, this.gbuilder)",
"15" :  "(77,89, option)",
"16" :  "(81,(81,82), i)",
"17" :  "(81,(81,84), i)",
"18" :  "(81,82, i)",
"19" :  "(84,89, option)"},{ "Name" : "createOption" ,
"Duas" : 32,
"0" :  "(105,120, this)",
"1" :  "(105,121, this)",
"2" :  "(105,122, this)",
"3" :  "(105,123, this)",
"4" :  "(105,125, this)",
"5" :  "(105,106, this)",
"6" :  "(105,107, this)",
"7" :  "(105,114, this)",
"8" :  "(105,112, this)",
"9" :  "(105,109, this)",
"10" :  "(105,(105,106), type)",
"11" :  "(105,(105,117), type)",
"12" :  "(105,107, type)",
"13" :  "(105,(111,112), type)",
"14" :  "(105,(111,114), type)",
"15" :  "(105,123, required)",
"16" :  "(105,(108,109), required)",
"17" :  "(105,(108,111), required)",
"18" :  "(105,122, opt)",
"19" :  "(105,106, this.abuilder)",
"20" :  "(105,107, this.abuilder)",
"21" :  "(105,114, this.abuilder)",
"22" :  "(105,112, this.abuilder)",
"23" :  "(105,109, this.abuilder)",
"24" :  "(105,120, this.obuilder)",
"25" :  "(105,121, this.obuilder)",
"26" :  "(105,122, this.obuilder)",
"27" :  "(105,123, this.obuilder)",
"28" :  "(105,125, this.obuilder)",
"29" :  "(105,125, this.options)",
"30" :  "(114,121, argument)",
"31" :  "(117,121, argument)"},{ "Name" : "withPattern" ,
"Duas" : 42,
"0" :  "(133,170, this)",
"1" :  "(133,160, this)",
"2" :  "(133,141, pattern)",
"3" :  "(133,(140,141), sz)",
"4" :  "(133,(140,169), sz)",
"5" :  "(135,(169,170), opt)",
"6" :  "(135,(169,172), opt)",
"7" :  "(135,170, opt)",
"8" :  "(135,(159,160), opt)",
"9" :  "(135,(159,165), opt)",
"10" :  "(135,160, opt)",
"11" :  "(137,170, type)",
"12" :  "(137,160, type)",
"13" :  "(138,170, required)",
"14" :  "(138,160, required)",
"15" :  "(140,(140,141), i)",
"16" :  "(140,(140,169), i)",
"17" :  "(140,141, i)",
"18" :  "(140,140, i)",
"19" :  "(141,(143,159), ch)",
"20" :  "(141,(143,145), ch)",
"21" :  "(141,(143,156), ch)",
"22" :  "(141,156, ch)",
"23" :  "(141,165, ch)",
"24" :  "(145,170, required)",
"25" :  "(145,160, required)",
"26" :  "(156,170, type)",
"27" :  "(156,160, type)",
"28" :  "(161,170, required)",
"29" :  "(161,160, required)",
"30" :  "(162,170, type)",
"31" :  "(162,160, type)",
"32" :  "(165,(169,170), opt)",
"33" :  "(165,(169,172), opt)",
"34" :  "(165,170, opt)",
"35" :  "(165,(159,160), opt)",
"36" :  "(165,(159,165), opt)",
"37" :  "(165,160, opt)",
"38" :  "(140,(140,141), i)",
"39" :  "(140,(140,169), i)",
"40" :  "(140,141, i)",
"41" :  "(140,140, i)"},{ "Name" : "validator" ,
"Duas" : 8,
"0" :  "(175,(175,199), c)",
"1" :  "(175,(175,187), c)",
"2" :  "(175,(175,185), c)",
"3" :  "(175,(175,195), c)",
"4" :  "(175,(175,181), c)",
"5" :  "(175,(175,197), c)",
"6" :  "(175,(175,189), c)",
"7" :  "(175,(175,177), c)"}]
}