{
"Class" : "org.jsoup.nodes.Attribute", 
"Methods" : [{ "Name" : "setKey" ,
"Duas" : 16,
"0" :  "(64,(67,68), this)",
"1" :  "(64,(67,72), this)",
"2" :  "(64,72, this)",
"3" :  "(64,68, this)",
"4" :  "(64,70, this)",
"5" :  "(64,(67,68), this.parent)",
"6" :  "(64,(67,72), this.parent)",
"7" :  "(64,68, this.parent)",
"8" :  "(64,70, this.parent)",
"9" :  "(64,68, this.key)",
"10" :  "(64,70, this.keys)",
"11" :  "(65,72, key)",
"12" :  "(65,70, key)",
"13" :  "(68,(69,70), i)",
"14" :  "(68,(69,72), i)",
"15" :  "(68,70, i)"},{ "Name" : "setValue" ,
"Duas" : 17,
"0" :  "(88,(89,90), this)",
"1" :  "(88,(89,94), this)",
"2" :  "(88,94, this)",
"3" :  "(88,90, this)",
"4" :  "(88,92, this)",
"5" :  "(88,94, val)",
"6" :  "(88,92, val)",
"7" :  "(88,(89,90), this.parent)",
"8" :  "(88,(89,94), this.parent)",
"9" :  "(88,90, this.parent)",
"10" :  "(88,92, this.parent)",
"11" :  "(88,90, this.key)",
"12" :  "(88,92, this.vals)",
"13" :  "(88,95, oldVal)",
"14" :  "(90,(91,92), i)",
"15" :  "(90,(91,94), i)",
"16" :  "(90,92, i)"},{ "Name" : "html" ,
"Duas" : 11,
"0" :  "(114,(115,116), key)",
"1" :  "(114,(115,120), key)",
"2" :  "(114,(115,116), val)",
"3" :  "(114,(115,120), val)",
"4" :  "(114,117, val)",
"5" :  "(114,116, accum)",
"6" :  "(114,117, accum)",
"7" :  "(114,118, accum)",
"8" :  "(114,(115,116), out)",
"9" :  "(114,(115,120), out)",
"10" :  "(114,117, out)"},{ "Name" : "isDataAttribute" ,
"Duas" : 4,
"0" :  "(151,(151,151), key)",
"1" :  "(151,(151,151), key)",
"2" :  "(151,(151,151), key)",
"3" :  "(151,(151,151), key)"},{ "Name" : "shouldCollapseAttribute" ,
"Duas" : 14,
"0" :  "(165,(165,165), key)",
"1" :  "(165,(165,165), key)",
"2" :  "(165,(165,165), key)",
"3" :  "(165,(165,165), key)",
"4" :  "(165,(165,165), val)",
"5" :  "(165,(165,165), val)",
"6" :  "(165,(165,165), val)",
"7" :  "(165,(165,165), val)",
"8" :  "(165,(165,165), val)",
"9" :  "(165,(165,165), val)",
"10" :  "(165,(165,165), out)",
"11" :  "(165,(165,165), out)",
"12" :  "(165,(165,165), html)",
"13" :  "(165,(165,165), html)"},{ "Name" : "isBooleanAttribute" ,
"Duas" : 10,
"0" :  "(174,(174,174), this)",
"1" :  "(174,(174,174), this)",
"2" :  "(174,(174,174), this)",
"3" :  "(174,(174,174), this)",
"4" :  "(174,(174,174), booleanAttributes)",
"5" :  "(174,(174,174), booleanAttributes)",
"6" :  "(174,(174,174), this.key)",
"7" :  "(174,(174,174), this.key)",
"8" :  "(174,(174,174), this.val)",
"9" :  "(174,(174,174), this.val)"},{ "Name" : "isBooleanAttribute" ,
"Duas" : 4,
"0" :  "(181,(181,181), key)",
"1" :  "(181,(181,181), key)",
"2" :  "(181,(181,181), booleanAttributes)",
"3" :  "(181,(181,181), booleanAttributes)"},{ "Name" : "equals" ,
"Duas" : 39,
"0" :  "(186,(186,186), this)",
"1" :  "(186,(186,187), this)",
"2" :  "(186,(187,187), this)",
"3" :  "(186,(187,188), this)",
"4" :  "(186,(189,189), this)",
"5" :  "(186,(189,189), this)",
"6" :  "(186,(190,190), this)",
"7" :  "(186,(190,190), this)",
"8" :  "(186,190, this)",
"9" :  "(186,(189,189), this)",
"10" :  "(186,(189,190), this)",
"11" :  "(186,(186,186), o)",
"12" :  "(186,(186,187), o)",
"13" :  "(186,(187,187), o)",
"14" :  "(186,(187,187), o)",
"15" :  "(186,(187,187), o)",
"16" :  "(186,(187,188), o)",
"17" :  "(186,188, o)",
"18" :  "(186,(189,189), this.key)",
"19" :  "(186,(189,189), this.key)",
"20" :  "(186,(189,189), this.key)",
"21" :  "(186,(189,190), this.key)",
"22" :  "(186,(190,190), this.val)",
"23" :  "(186,(190,190), this.val)",
"24" :  "(186,190, this.val)",
"25" :  "(188,(189,189), attribute)",
"26" :  "(188,(189,190), attribute)",
"27" :  "(188,(190,190), attribute)",
"28" :  "(188,(190,190), attribute)",
"29" :  "(188,190, attribute)",
"30" :  "(188,(189,189), attribute)",
"31" :  "(188,(189,190), attribute)",
"32" :  "(188,(189,189), attribute.key)",
"33" :  "(188,(189,190), attribute.key)",
"34" :  "(188,(189,189), attribute.key)",
"35" :  "(188,(189,190), attribute.key)",
"36" :  "(188,(190,190), attribute.val)",
"37" :  "(188,(190,190), attribute.val)",
"38" :  "(188,190, attribute.val)"},{ "Name" : "hashCode" ,
"Duas" : 11,
"0" :  "(195,(195,195), this)",
"1" :  "(195,(195,195), this)",
"2" :  "(195,195, this)",
"3" :  "(195,(196,196), this)",
"4" :  "(195,(196,196), this)",
"5" :  "(195,(195,195), this.key)",
"6" :  "(195,(195,195), this.key)",
"7" :  "(195,195, this.key)",
"8" :  "(195,(196,196), this.val)",
"9" :  "(195,(196,196), this.val)",
"10" :  "(195,196, result)"}]
}